Workbook

Sheet Description
C5: LVMH Group Digital Projects Tracking Board
C14: Legend Explaination
E16: Maison is involved in Status of Data
C22: Ideation | E22: Project has been mentioned but not turned into action
C25: Q1-Pilot | E25: Project is in POC or Pilot Phase in Q1
C26: Q2-Pilot | E26: Project is in POC or Pilot Phase in Q2
C27: Q3-Pilot | E27: Project is in POC or Pilot Phase in Q3
C28: Q4-Pilot | E28: Project is in POC or Pilot Phase in Q4
C31: Q1-Scale | E31: Project deployed as daily usage in Q1
C32: Q2-Scale | E32: Project deployed as daily usage in Q2
C33: Q3-Scale | E33: Project deployed as daily usage in Q3
C34: Q4-Scale | E34: Project deployed as daily usage in Q4
C37: Done | E37: Project has been delivered
C38: Run | E38: Project has been delivered & continually in production

Sheet Maison Dimension Tracking Table
H1: Fashion & Leather Goods | S1: Watch & Jewellery | Z1: Beauty | AC1: Selective Retailing | AD1: Wine
G2: 23 | H2: Louis Vuitton | I2: Christine Dior Couture | J2: Loro Piana | K2: Fendi | L2: Celine | M2: Loewe | N2: Givenchy | O2: Kenzo | P2: Berluti | Q2: Marc Jocobs | R2: Rimowa | S2: Tiffany | T2: Bvlgari | U2: Chaumet | V2: Fred | W2: Hublot | X2: TAG Heuer | Y2: Zenith | Z2: Perfume Christine Dior | AA2: Guerlain | AB2: Beauty Division | AC2: Sephora | AD2: MHD
H3: =_xlfn.TEXTJOIN(" | ",TRUE,"Total: "&COUNTIF(H8:H40,"Q*")+COUNTIF(H8:H40,"Ideation")) -> Total: 7 | I3: =_xlfn.TEXTJOIN(" | ",TRUE,"Total: "&COUNTIF(I8:I40,"Q*")+COUNTIF(I8:I40,"Ideation")) -> Total: 8 | J3: =_xlfn.TEXTJOIN(" | ",TRUE,"Total: "&COUNTIF(J8:J40,"Q*")+COUNTIF(J8:J40,"Ideation")) -> Total: 8 | K3: =_xlfn.TEXTJOIN(" | ",TRUE,"Total: "&COUNTIF(K8:K40,"Q*")+COUNTIF(K8:K40,"Ideation")) -> Total: 8 | L3: =_xlfn.TEXTJOIN(" | ",TRUE,"Total: "&COUNTIF(L8:L40,"Q*")+COUNTIF(L8:L40,"Ideation")) -> Total: 11 | M3: =_xlfn.TEXTJOIN(" | ",TRUE,"Total: "&COUNTIF(M8:M40,"Q*")+COUNTIF(M8:M40,"Ideation")) -> Total: 13 | N3: =_xlfn.TEXTJOIN(" | ",TRUE,"Total: "&COUNTIF(N8:N40,"Q*")+COUNTIF(N8:N40,"Ideation")) -> Total: 3 | O3: =_xlfn.TEXTJOIN(" | ",TRUE,"Total: "&COUNTIF(O8:O40,"Q*")+COUNTIF(O8:O40,"Ideation")) -> Total: 0 | ... AD3: =_xlfn.TEXTJOIN(" | ",TRUE,"Total: "&COUNTIF(AD8:AD40,"Q*")+COUNTIF(AD8:AD40,"Ideation")) -> Total: 1
H4: =_xlfn.TEXTJOIN(" | ",TRUE,"Ideation: "&COUNTIF(H8:H40,"Ideation")) -> Ideation: 4 | I4: =_xlfn.TEXTJOIN(" | ",TRUE,"Ideation: "&COUNTIF(I8:I40,"Ideation")) -> Ideation: 4 | J4: =_xlfn.TEXTJOIN(" | ",TRUE,"Ideation: "&COUNTIF(J8:J40,"Ideation")) -> Ideation: 5 | K4: =_xlfn.TEXTJOIN(" | ",TRUE,"Ideation: "&COUNTIF(K8:K40,"Ideation")) -> Ideation: 3 | L4: =_xlfn.TEXTJOIN(" | ",TRUE,"Ideation: "&COUNTIF(L8:L40,"Ideation")) -> Ideation: 5 | M4: =_xlfn.TEXTJOIN(" | ",TRUE,"Ideation: "&COUNTIF(M8:M40,"Ideation")) -> Ideation: 4 | N4: =_xlfn.TEXTJOIN(" | ",TRUE,"Ideation: "&COUNTIF(N8:N40,"Ideation")) -> Ideation: 1 | O4: =_xlfn.TEXTJOIN(" | ",TRUE,"Ideation: "&COUNTIF(O8:O40,"Ideation")) -> Ideation: 0 | ... AD4: =_xlfn.TEXTJOIN(" | ",TRUE,"Ideation: "&COUNTIF(AD8:AD40,"Ideation")) -> Ideation: 0
H5: =_xlfn.TEXTJOIN(" | ",TRUE,"Pilot: "&COUNTIF(H8:H40,"*Pilot*"),"Scale: "&COUNTIF(H8:H40,"*Scale*")) -> Pilot: 2 | Scale: 1 | I5: =_xlfn.TEXTJOIN(" | ",TRUE,"Pilot: "&COUNTIF(I8:I40,"*Pilot*"),"Scale: "&COUNTIF(I8:I40,"*Scale*"),) -> Pilot: 2 | Scale: 2 | J5: =_xlfn.TEXTJOIN(" | ",TRUE,"Pilot: "&COUNTIF(J8:J40,"*Pilot*"),"Scale: "&COUNTIF(J8:J40,"*Scale*"),) -> Pilot: 2 | Scale: 1 | K5: =_xlfn.TEXTJOIN(" | ",TRUE,"Pilot: "&COUNTIF(K8:K40,"*Pilot*"),"Scale: "&COUNTIF(K8:K40,"*Scale*"),) -> Pilot: 4 | Scale: 1 | L5: =_xlfn.TEXTJOIN(" | ",TRUE,"Pilot: "&COUNTIF(L8:L40,"*Pilot*"),"Scale: "&COUNTIF(L8:L40,"*Scale*"),) -> Pilot: 4 | Scale: 2 | M5: =_xlfn.TEXTJOIN(" | ",TRUE,"Pilot: "&COUNTIF(M8:M40,"*Pilot*"),"Scale: "&COUNTIF(M8:M40,"*Scale*"),) -> Pilot: 7 | Scale: 2 | N5: =_xlfn.TEXTJOIN(" | ",TRUE,"Pilot: "&COUNTIF(N8:N40,"*Pilot*"),"Scale: "&COUNTIF(N8:N40,"*Scale*"),) -> Pilot: 2 | Scale: 0 | O5: =_xlfn.TEXTJOIN(" | ",TRUE,"Pilot: "&COUNTIF(O8:O40,"*Pilot*"),"Scale: "&COUNTIF(O8:O40,"*Scale*"),) -> Pilot: 0 | Scale: 0 | P5: =_xlfn.TEXTJOIN(" | ",TRUE,"Pilot: "&COUNTIF(P8:P40,"*Pilot*"),"Scale: "&COUNTIF(P8:P40,"*Scale*"),) -> Pilot: 2 | Scale: 0 | ... AD5: =_xlfn.TEXTJOIN(" | ",TRUE,"Pilot: "&COUNTIF(AD8:AD40,"*Pilot*"),"Scale: "&COUNTIF(AD8:AD40,"*Scale*"),) -> Pilot: 0 | Scale: 1
G6: Maison AI Champaion | H6: Gary CHU | I6: Winnie AW | J6: Elaine TANG | K6: Monica CHEN | L6: Matthieu PETRI | M6: Florian MULLER | P6: Lucas YU | R6: Eric CHEN | S6: Josh WU | T6: Maggie ZHU | U6: Amy WU | V6: Sueann SU | X6: Kiki MI | Y6: Kelly WU | Z6: Shen XU | AA6: Eric HAN | AB6: Raymond DING | AC6: Sherry DENG
C7: Priority | D7: Owner | E7: Project Name | G7: Statics | H7: Rachael JIANG | I7: Mars YU | J7: Rachael JIANG | K7: Wendy CHEN | L7: Livia GAO | M7: Yuanne CHANG | N7: Xintong YAN | O7: TBD | P7: Yuanne CHANG | Q7: TBD | R7: Wendy CHEN | S7: Candy HOU | T7: Chenlong WANG | U7: Qiwen MO | V7: Rikka CHEN | W7: Wendy CHEN | X7: Qiwen MO | Y7: Qiwen MO | Z7: Chenlong WANG | AA7: Rikka CHEN | AB7: Wendy CHEN | AC7: Qia CHEN | AD7: Mars Yu
A8: DATA & AI | B8: Client development | C8: QW | D8: Mars YU | E8: Enrich project scaling | G8: =_xlfn.TEXTJOIN(" | ",TRUE,"Total: "&COUNTIF(H8:AD8,"Q*")+COUNTIF(H8:AD8,"Ideation")+COUNTIF(H8:AD8,"Done")+COUNTIF(H8:AD8,"Run"),"Ideation: "&COUNTIF(H8:AD8,"Ideation"),"Pilot: "&COUNTIF(H8:AD8,"*Pilot"),"Scale: "&COUNTIF(H8:AD8,"*Scale"),"Run: "&COUNTIF(H8:AD8,"Run"),"Done: "&COUNTIF(H8:AD8,"Done")) -> Total: 17 | Ideation: 4 | Pilot: 2 | Scale: 3 | Run: 8 | Done: 0 | I8: Ideation | J8: Run | K8: Run | L8: Run | M8: Run | P8: Q2-Pilot | R8: Ideation | S8: Run | T8: Run | U8: Run | V8: Run | W8: Q1-Scale | Y8: Q4-Scale | Z8: Ideation | AA8: Ideation | AC8: Q4-Pilot | AD8: Q3-Scale
B9: Client development | C9: QW | D9: Chenlong WANG | E9: 【Advanced Journey 】High potential one-timer/repeater | G9: =_xlfn.TEXTJOIN(" | ",TRUE,"Total: "&COUNTIF(H9:AD9,"Q*")+COUNTIF(H9:AD9,"Ideation")+COUNTIF(H9:AD9,"Done")+COUNTIF(H9:AD9,"Run"),"Ideation: "&COUNTIF(H9:AD9,"Ideation"),"Pilot: "&COUNTIF(H9:AD9,"*Pilot"),"Scale: "&COUNTIF(H9:AD9,"*Scale"),"Run: "&COUNTIF(H9:AD9,"Run"),"Done: "&COUNTIF(H9:AD9,"Done")) -> Total: 7 | Ideation: 0 | Pilot: 0 | Scale: 0 | Run: 7 | Done: 0 | J9: Run | K9: Run | L9: Run | M9: Run | S9: Run | T9: Run | U9: Run
B10: Client development | C10: QW | D10: Chenlong WANG | E10: 【Advanced Journey 】High potential one-timer/repeater causal inference | G10: =_xlfn.TEXTJOIN(" | ",TRUE,"Total: "&COUNTIF(H10:AD10,"Q*")+COUNTIF(H10:AD10,"Ideation")+COUNTIF(H10:AD10,"Done")+COUNTIF(H10:AD10,"Run"),"Ideation: "&COUNTIF(H10:AD10,"Ideation"),"Pilot: "&COUNTIF(H10:AD10,"*Pilot"),"Scale: "&COUNTIF(H10:AD10,"*Scale"),"Run: "&COUNTIF(H10:AD10,"Run"),"Done: "&COUNTIF(H10:AD10,"Done")) -> Total: 1 | Ideation: 0 | Pilot: 1 | Scale: 0 | Run: 0 | Done: 0 | V10: Q3-Pilot
B11: Client development | C11: QW | D11: Xintong YAN | E11: 【Advanced Journey 】High potential client list orchestration | G11: =_xlfn.TEXTJOIN(" | ",TRUE,"Total: "&COUNTIF(H11:AD11,"Q*")+COUNTIF(H11:AD11,"Ideation")+COUNTIF(H11:AD11,"Done")+COUNTIF(H11:AD11,"Run"),"Ideation: "&COUNTIF(H11:AD11,"Ideation"),"Pilot: "&COUNTIF(H11:AD11,"*Pilot"),"Scale: "&COUNTIF(H11:AD11,"*Scale"),"Run: "&COUNTIF(H11:AD11,"Run"),"Done: "&COUNTIF(H11:AD11,"Done")) -> Total: 1 | Ideation: 0 | Pilot: 1 | Scale: 0 | Run: 0 | Done: 0 | T11: Q3-Pilot
B12: Client development | C12: QW | D12: Chenlong WANG | E12: 【Advanced Journey 】High potential propensity for collection | G12: =_xlfn.TEXTJOIN(" | ",TRUE,"Total: "&COUNTIF(H12:AD12,"Q*")+COUNTIF(H12:AD12,"Ideation")+COUNTIF(H12:AD12,"Done")+COUNTIF(H12:AD12,"Run"),"Ideation: "&COUNTIF(H12:AD12,"Ideation"),"Pilot: "&COUNTIF(H12:AD12,"*Pilot"),"Scale: "&COUNTIF(H12:AD12,"*Scale"),"Run: "&COUNTIF(H12:AD12,"Run"),"Done: "&COUNTIF(H12:AD12,"Done")) -> Total: 4 | Ideation: 1 | Pilot: 0 | Scale: 0 | Run: 2 | Done: 1 | N12: Done | S12: Ideation | T12: Run | U12: Run
B13: Client development | C13: QW | D13: Chenlong WANG | E13: 【Advanced Journey 】High potential VIC detection | G13: =_xlfn.TEXTJOIN(" | ",TRUE,"Total: "&COUNTIF(H13:AD13,"Q*")+COUNTIF(H13:AD13,"Ideation")+COUNTIF(H13:AD13,"Done")+COUNTIF(H13:AD13,"Run"),"Ideation: "&COUNTIF(H13:AD13,"Ideation"),"Pilot: "&COUNTIF(H13:AD13,"*Pilot"),"Scale: "&COUNTIF(H13:AD13,"*Scale"),"Run: "&COUNTIF(H13:AD13,"Run"),"Done: "&COUNTIF(H13:AD13,"Done")) -> Total: 1 | Ideation: 0 | Pilot: 0 | Scale: 1 | Run: 0 | Done: 0 | M13: Q3-Scale
B14: Client development | C14: QW | D14: Chenlong WANG | E14: 【Advanced Journey 】Product Recom DREAM 2.0 | G14: =_xlfn.TEXTJOIN(" | ",TRUE,"Total: "&COUNTIF(H14:AD14,"Q*")+COUNTIF(H14:AD14,"Ideation")+COUNTIF(H14:AD14,"Done")+COUNTIF(H14:AD14,"Run"),"Ideation: "&COUNTIF(H14:AD14,"Ideation"),"Pilot: "&COUNTIF(H14:AD14,"*Pilot"),"Scale: "&COUNTIF(H14:AD14,"*Scale"),"Run: "&COUNTIF(H14:AD14,"Run"),"Done: "&COUNTIF(H14:AD14,"Done")) -> Total: 6 | Ideation: 3 | Pilot: 3 | Scale: 0 | Run: 0 | Done: 0 | J14: Ideation | L14: Q4-Pilot | M14: Q4-Pilot | T14: Q2-Pilot | U14: Ideation | AB14: Ideation
B15: Client development | C15: QW | D15: Livia GAO | E15: 【Advanced Journey 】Total-look recommendation | G15: =_xlfn.TEXTJOIN(" | ",TRUE,"Total: "&COUNTIF(H15:AD15,"Q*")+COUNTIF(H15:AD15,"Ideation")+COUNTIF(H15:AD15,"Done")+COUNTIF(H15:AD15,"Run"),"Ideation: "&COUNTIF(H15:AD15,"Ideation"),"Pilot: "&COUNTIF(H15:AD15,"*Pilot"),"Scale: "&COUNTIF(H15:AD15,"*Scale"),"Run: "&COUNTIF(H15:AD15,"Run"),"Done: "&COUNTIF(H15:AD15,"Done")) -> Total: 2 | Ideation: 1 | Pilot: 1 | Scale: 0 | Run: 0 | Done: 0 | L15: Ideation | M15: Q4-Pilot
B16: Client development | C16: QW | D16: Chenlong WANG | E16: 【Clienteling】Gen AI Client Knowledge | G16: =_xlfn.TEXTJOIN(" | ",TRUE,"Total: "&COUNTIF(H16:AD16,"Q*")+COUNTIF(H16:AD16,"Ideation")+COUNTIF(H16:AD16,"Done")+COUNTIF(H16:AD16,"Run"),"Ideation: "&COUNTIF(H16:AD16,"Ideation"),"Pilot: "&COUNTIF(H16:AD16,"*Pilot"),"Scale: "&COUNTIF(H16:AD16,"*Scale"),"Run: "&COUNTIF(H16:AD16,"Run"),"Done: "&COUNTIF(H16:AD16,"Done")) -> Total: 6 | Ideation: 3 | Pilot: 3 | Scale: 0 | Run: 0 | Done: 0 | H16: Ideation | I16: Q4-Pilot | J16: Ideation | S16: Ideation | T16: Q4-Pilot | Z16: Q3-Pilot
C17: TT | D17: Mars YU | E17: Enlight + | G17: =_xlfn.TEXTJOIN(" | ",TRUE,"Total: "&COUNTIF(H17:AD17,"Q*")+COUNTIF(H17:AD17,"Ideation")+COUNTIF(H17:AD17,"Done")+COUNTIF(H17:AD17,"Run"),"Ideation: "&COUNTIF(H17:AD17,"Ideation"),"Pilot: "&COUNTIF(H17:AD17,"*Pilot"),"Scale: "&COUNTIF(H17:AD17,"*Scale"),"Run: "&COUNTIF(H17:AD17,"Run"),"Done: "&COUNTIF(H17:AD17,"Done")) -> Total: 0 | Ideation: 0 | Pilot: 0 | Scale: 0 | Run: 0 | Done: 0
C18: TT | D18: Mars YU | E18: State of Data（June） | G18: =_xlfn.TEXTJOIN(" | ",TRUE,"Total: "&COUNTIF(H18:AD18,"Q*")+COUNTIF(H18:AD18,"Ideation")+COUNTIF(H18:AD18,"Done")+COUNTIF(H18:AD18,"Run"),"Ideation: "&COUNTIF(H18:AD18,"Ideation"),"Pilot: "&COUNTIF(H18:AD18,"*Pilot"),"Scale: "&COUNTIF(H18:AD18,"*Scale"),"Run: "&COUNTIF(H18:AD18,"Run"),"Done: "&COUNTIF(H18:AD18,"Done")) -> Total: 9 | Ideation: 0 | Pilot: 0 | Scale: 0 | Run: 0 | Done: 9 | H18: Done | I18: Done | J18: Done | K18: Done | L18: Done | M18: Done | S18: Done | T18: Done | U18: Done
A19: CLIENT DEVELOPMENT | B19: Client development | C19: QW | D19: Qiwen MO | E19: 【Marketing Automation 】Personalized journeys through QA migration, upgrades, and orchestration | G19: =_xlfn.TEXTJOIN(" | ",TRUE,"Total: "&COUNTIF(H19:AD19,"Q*")+COUNTIF(H19:AD19,"Ideation")+COUNTIF(H19:AD19,"Done")+COUNTIF(H19:AD19,"Run"),"Ideation: "&COUNTIF(H19:AD19,"Ideation"),"Pilot: "&COUNTIF(H19:AD19,"*Pilot"),"Scale: "&COUNTIF(H19:AD19,"*Scale"),"Run: "&COUNTIF(H19:AD19,"Run"),"Done: "&COUNTIF(H19:AD19,"Done")) -> Total: 12 | Ideation: 0 | Pilot: 4 | Scale: 8 | Run: 0 | Done: 0 | H19: Q3-Pilot | I19: Q1-Scale | J19: Q1-Scale | K19: Q2-Scale | L19: Q3-Pilot | M19: Q4-Pilot | N19: Q4-Pilot | S19: Q3-Scale | T19: Q1-Scale | U19: Q3-Scale | Z19: Q1-Scale | AA19: Q1-Scale
B20: Client development | C20: BB | D20: Qiwen MO | E20: 【Gen AI Content Hub】Content Tagging & Distrubution | G20: =_xlfn.TEXTJOIN(" | ",TRUE,"Total: "&COUNTIF(H20:AD20,"Q*")+COUNTIF(H20:AD20,"Ideation")+COUNTIF(H20:AD20,"Done")+COUNTIF(H20:AD20,"Run"),"Ideation: "&COUNTIF(H20:AD20,"Ideation"),"Pilot: "&COUNTIF(H20:AD20,"*Pilot"),"Scale: "&COUNTIF(H20:AD20,"*Scale"),"Run: "&COUNTIF(H20:AD20,"Run"),"Done: "&COUNTIF(H20:AD20,"Done")) -> Total: 3 | Ideation: 0 | Pilot: 2 | Scale: 1 | Run: 0 | Done: 0 | S20: Q2-Scale | T20: Q2-Pilot | U20: Q3-Pilot
B21: Client development | C21: QW | D21: Candy HOU | E21: 【Clienteling】Gen AI Contextual Outreach | G21: =_xlfn.TEXTJOIN(" | ",TRUE,"Total: "&COUNTIF(H21:AD21,"Q*")+COUNTIF(H21:AD21,"Ideation")+COUNTIF(H21:AD21,"Done")+COUNTIF(H21:AD21,"Run"),"Ideation: "&COUNTIF(H21:AD21,"Ideation"),"Pilot: "&COUNTIF(H21:AD21,"*Pilot"),"Scale: "&COUNTIF(H21:AD21,"*Scale"),"Run: "&COUNTIF(H21:AD21,"Run"),"Done: "&COUNTIF(H21:AD21,"Done")) -> Total: 9 | Ideation: 3 | Pilot: 5 | Scale: 1 | Run: 0 | Done: 0 | H21: Ideation | I21: Q4-Pilot | L21: Ideation | R21: Ideation | S21: Q3-Scale | T21: Q2-Pilot | U21: Q3-Pilot | AA21: Q3-Pilot | AB21: Q3-Pilot
B22: Client development | C22: QW | D22: Candy HOU | E22: 【Client Community】CRM upskilling and community | G22: =_xlfn.TEXTJOIN(" | ",TRUE,"Total: "&COUNTIF(H22:AD22,"Q*")+COUNTIF(H22:AD22,"Ideation")+COUNTIF(H22:AD22,"Done")+COUNTIF(H22:AD22,"Run"),"Ideation: "&COUNTIF(H22:AD22,"Ideation"),"Pilot: "&COUNTIF(H22:AD22,"*Pilot"),"Scale: "&COUNTIF(H22:AD22,"*Scale"),"Run: "&COUNTIF(H22:AD22,"Run"),"Done: "&COUNTIF(H22:AD22,"Done")) -> Total: 17 | Ideation: 0 | Pilot: 0 | Scale: 0 | Run: 0 | Done: 17 | H22: Done | I22: Done | J22: Done | K22: Done | L22: Done | M22: Done | O22: Done | P22: Done | R22: Done | S22: Done | T22: Done | U22: Done | V22: Done | Z22: Done | AA22: Done | AB22: Done | AD22: Done
B23: Client development | C23: TT | D23: Qiwen MO | E23: 【Clienteling】WeCom tools benchmark and feature innovation | G23: =_xlfn.TEXTJOIN(" | ",TRUE,"Total: "&COUNTIF(H23:AD23,"Q*")+COUNTIF(H23:AD23,"Ideation")+COUNTIF(H23:AD23,"Done")+COUNTIF(H23:AD23,"Run"),"Ideation: "&COUNTIF(H23:AD23,"Ideation"),"Pilot: "&COUNTIF(H23:AD23,"*Pilot"),"Scale: "&COUNTIF(H23:AD23,"*Scale"),"Run: "&COUNTIF(H23:AD23,"Run"),"Done: "&COUNTIF(H23:AD23,"Done")) -> Total: 16 | Ideation: 0 | Pilot: 0 | Scale: 0 | Run: 0 | Done: 16 | H23: Done | I23: Done | J23: Done | K23: Done | L23: Done | M23: Done | P23: Done | R23: Done | S23: Done | T23: Done | U23: Done | V23: Done | W23: Done | X23: Done | Z23: Done | AA23: Done
B24: Client development | C24: QW | D24: TBD | E24: 【KOS】AI solutions (scanning, content assistant, task management ) | G24: =_xlfn.TEXTJOIN(" | ",TRUE,"Total: "&COUNTIF(H24:AD24,"Q*")+COUNTIF(H24:AD24,"Ideation")+COUNTIF(H24:AD24,"Done")+COUNTIF(H24:AD24,"Run"),"Ideation: "&COUNTIF(H24:AD24,"Ideation"),"Pilot: "&COUNTIF(H24:AD24,"*Pilot"),"Scale: "&COUNTIF(H24:AD24,"*Scale"),"Run: "&COUNTIF(H24:AD24,"Run"),"Done: "&COUNTIF(H24:AD24,"Done")) -> Total: 7 | Ideation: 4 | Pilot: 2 | Scale: 1 | Run: 0 | Done: 0 | L24: Ideation | M24: Ideation | S24: Q1-Scale | U24: Ideation | X24: Ideation | AA24: Q3-Pilot | AB24: Q3-Pilot
B25: Client development | C25: TT | D25: TBD | E25: 【KOS Community】 Maison operation lead training, KOS Day（September） | G25: =_xlfn.TEXTJOIN(" | ",TRUE,"Total: "&COUNTIF(H25:AD25,"Q*")+COUNTIF(H25:AD25,"Ideation")+COUNTIF(H25:AD25,"Done")+COUNTIF(H25:AD25,"Run"),"Ideation: "&COUNTIF(H25:AD25,"Ideation"),"Pilot: "&COUNTIF(H25:AD25,"*Pilot"),"Scale: "&COUNTIF(H25:AD25,"*Scale"),"Run: "&COUNTIF(H25:AD25,"Run"),"Done: "&COUNTIF(H25:AD25,"Done")) -> Total: 0 | Ideation: 0 | Pilot: 0 | Scale: 0 | Run: 0 | Done: 0
A26: OMNI. RETAIL | B26: Omni retail | C26: QW | D26: Wendy CHEN | E26: China AI omni landscape strategy playbook 1) Drive to Store | G26: =_xlfn.TEXTJOIN(" | ",TRUE,"Total: "&COUNTIF(H26:AD26,"Q*")+COUNTIF(H26:AD26,"Ideation")+COUNTIF(H26:AD26,"Done")+COUNTIF(H26:AD26,"Run"),"Ideation: "&COUNTIF(H26:AD26,"Ideation"),"Pilot: "&COUNTIF(H26:AD26,"*Pilot"),"Scale: "&COUNTIF(H26:AD26,"*Scale"),"Run: "&COUNTIF(H26:AD26,"Run"),"Done: "&COUNTIF(H26:AD26,"Done")) -> Total: 2 | Ideation: 1 | Pilot: 1 | Scale: 0 | Run: 0 | Done: 0 | J26: Q4-Pilot | T26: Ideation
B27: Omni retail | C27: BB | D27: Wendy CHEN | E27: China AI omni landscape strategy playbook 2) Agentic commerce | G27: =_xlfn.TEXTJOIN(" | ",TRUE,"Total: "&COUNTIF(H27:AD27,"Q*")+COUNTIF(H27:AD27,"Ideation")+COUNTIF(H27:AD27,"Done")+COUNTIF(H27:AD27,"Run"),"Ideation: "&COUNTIF(H27:AD27,"Ideation"),"Pilot: "&COUNTIF(H27:AD27,"*Pilot"),"Scale: "&COUNTIF(H27:AD27,"*Scale"),"Run: "&COUNTIF(H27:AD27,"Run"),"Done: "&COUNTIF(H27:AD27,"Done")) -> Total: 11 | Ideation: 7 | Pilot: 4 | Scale: 0 | Run: 0 | Done: 0 | H27: Ideation | K27: Q3-Pilot | M27: Ideation | N27: Ideation | R27: Q4-Pilot | S27: Ideation | T27: Ideation | U27: Ideation | Z27: Ideation | AA27: Q3-Pilot | AC27: Q4-Pilot
B28: Omni retail | C28: TT | D28: Wendy CHEN | E28: Al for omni excellence - 1) Tracking Lab | G28: =_xlfn.TEXTJOIN(" | ",TRUE,"Total: "&COUNTIF(H28:AD28,"Q*")+COUNTIF(H28:AD28,"Ideation")+COUNTIF(H28:AD28,"Done")+COUNTIF(H28:AD28,"Run"),"Ideation: "&COUNTIF(H28:AD28,"Ideation"),"Pilot: "&COUNTIF(H28:AD28,"*Pilot"),"Scale: "&COUNTIF(H28:AD28,"*Scale"),"Run: "&COUNTIF(H28:AD28,"Run"),"Done: "&COUNTIF(H28:AD28,"Done")) -> Total: 4 | Ideation: 1 | Pilot: 0 | Scale: 1 | Run: 2 | Done: 0 | J28: Run | L28: Q2-Scale | M28: Ideation | U28: Run
B29: Omni retail | C29: TT | D29: Wendy CHEN | E29: Al for omni excellence - 2) Product recommendation | G29: =_xlfn.TEXTJOIN(" | ",TRUE,"Total: "&COUNTIF(H29:AD29,"Q*")+COUNTIF(H29:AD29,"Ideation")+COUNTIF(H29:AD29,"Done")+COUNTIF(H29:AD29,"Run"),"Ideation: "&COUNTIF(H29:AD29,"Ideation"),"Pilot: "&COUNTIF(H29:AD29,"*Pilot"),"Scale: "&COUNTIF(H29:AD29,"*Scale"),"Run: "&COUNTIF(H29:AD29,"Run"),"Done: "&COUNTIF(H29:AD29,"Done")) -> Total: 4 | Ideation: 2 | Pilot: 2 | Scale: 0 | Run: 0 | Done: 0 | K29: Ideation | L29: Q4-Pilot | M29: Q4-Pilot | R29: Ideation
B30: Omni retail | C30: TT | D30: Wendy CHEN | E30: Al for omni excellence - 3) Smart Search | G30: =_xlfn.TEXTJOIN(" | ",TRUE,"Total: "&COUNTIF(H30:AD30,"Q*")+COUNTIF(H30:AD30,"Ideation")+COUNTIF(H30:AD30,"Done")+COUNTIF(H30:AD30,"Run"),"Ideation: "&COUNTIF(H30:AD30,"Ideation"),"Pilot: "&COUNTIF(H30:AD30,"*Pilot"),"Scale: "&COUNTIF(H30:AD30,"*Scale"),"Run: "&COUNTIF(H30:AD30,"Run"),"Done: "&COUNTIF(H30:AD30,"Done")) -> Total: 6 | Ideation: 4 | Pilot: 1 | Scale: 0 | Run: 1 | Done: 0 | H30: Q3-Pilot | I30: Run | J30: Ideation | K30: Ideation | L30: Ideation | R30: Ideation
B31: Omni retail | C31: TT | D31: Rikka CHEN | E31: Omni incentive orchestration | G31: =_xlfn.TEXTJOIN(" | ",TRUE,"Total: "&COUNTIF(H31:AD31,"Q*")+COUNTIF(H31:AD31,"Ideation")+COUNTIF(H31:AD31,"Done")+COUNTIF(H31:AD31,"Run"),"Ideation: "&COUNTIF(H31:AD31,"Ideation"),"Pilot: "&COUNTIF(H31:AD31,"*Pilot"),"Scale: "&COUNTIF(H31:AD31,"*Scale"),"Run: "&COUNTIF(H31:AD31,"Run"),"Done: "&COUNTIF(H31:AD31,"Done")) -> Total: 2 | Ideation: 1 | Pilot: 0 | Scale: 0 | Run: 1 | Done: 0 | H31: Run | T31: Ideation
B32: Omni retail | C32: TT | D32: Rikka CHEN | E32: VoC (NPS) | G32: =_xlfn.TEXTJOIN(" | ",TRUE,"Total: "&COUNTIF(H32:AD32,"Q*")+COUNTIF(H32:AD32,"Ideation")+COUNTIF(H32:AD32,"Done")+COUNTIF(H32:AD32,"Run"),"Ideation: "&COUNTIF(H32:AD32,"Ideation"),"Pilot: "&COUNTIF(H32:AD32,"*Pilot"),"Scale: "&COUNTIF(H32:AD32,"*Scale"),"Run: "&COUNTIF(H32:AD32,"Run"),"Done: "&COUNTIF(H32:AD32,"Done")) -> Total: 14 | Ideation: 0 | Pilot: 0 | Scale: 2 | Run: 12 | Done: 0 | H32: Run | I32: Run | J32: Run | L32: Q3-Scale | M32: Q4-Scale | R32: Run | S32: Run | T32: Run | U32: Run | V32: Run | Z32: Run | AA32: Run | AB32: Run | AC32: Run
B33: Omni retail | C33: TT | D33: Rikka CHEN | E33: Al training for omni-retail | G33: =_xlfn.TEXTJOIN(" | ",TRUE,"Total: "&COUNTIF(H33:AD33,"Q*")+COUNTIF(H33:AD33,"Ideation")+COUNTIF(H33:AD33,"Done")+COUNTIF(H33:AD33,"Run"),"Ideation: "&COUNTIF(H33:AD33,"Ideation"),"Pilot: "&COUNTIF(H33:AD33,"*Pilot"),"Scale: "&COUNTIF(H33:AD33,"*Scale"),"Run: "&COUNTIF(H33:AD33,"Run"),"Done: "&COUNTIF(H33:AD33,"Done")) -> Total: 10 | Ideation: 5 | Pilot: 4 | Scale: 1 | Run: 0 | Done: 0 | H33: Q4-Scale | K33: Q2-Pilot | M33: Ideation | R33: Q4-Pilot | S33: Ideation | T33: Ideation | V33: Ideation | Y33: Ideation | AA33: Q4-Pilot | AC33: Q4-Pilot
B34: Omni retail | C34: TT | D34: Qia CHEN | E34: Gen-AI CSC | G34: =_xlfn.TEXTJOIN(" | ",TRUE,"Total: "&COUNTIF(H34:AD34,"Q*")+COUNTIF(H34:AD34,"Ideation")+COUNTIF(H34:AD34,"Done")+COUNTIF(H34:AD34,"Run"),"Ideation: "&COUNTIF(H34:AD34,"Ideation"),"Pilot: "&COUNTIF(H34:AD34,"*Pilot"),"Scale: "&COUNTIF(H34:AD34,"*Scale"),"Run: "&COUNTIF(H34:AD34,"Run"),"Done: "&COUNTIF(H34:AD34,"Done")) -> Total: 4 | Ideation: 2 | Pilot: 0 | Scale: 1 | Run: 1 | Done: 0 | H34: Run | I34: Q3-Scale | S34: Ideation | T34: Ideation
A35: MARKETING | B35: Marketing | C35: BB | D35: Qia CHEN | E35: 【Gen AI Content Hub】Asset Production & Distribution | G35: =_xlfn.TEXTJOIN(" | ",TRUE,"Total: "&COUNTIF(H35:AD35,"Q*")+COUNTIF(H35:AD35,"Ideation")+COUNTIF(H35:AD35,"Done")+COUNTIF(H35:AD35,"Run"),"Ideation: "&COUNTIF(H35:AD35,"Ideation"),"Pilot: "&COUNTIF(H35:AD35,"*Pilot"),"Scale: "&COUNTIF(H35:AD35,"*Scale"),"Run: "&COUNTIF(H35:AD35,"Run"),"Done: "&COUNTIF(H35:AD35,"Done")) -> Total: 8 | Ideation: 4 | Pilot: 2 | Scale: 0 | Run: 2 | Done: 0 | K35: Ideation | N35: Run | P35: Ideation | S35: Run | U35: Ideation | Y35: Q2-Pilot | AA35: Ideation | AC35: Q3-Pilot
B36: Marketing | C36: BB | D36: Qia CHEN | E36: 【Gen AI Content Hub】Asset Production & Distribution - LucIA | G36: =_xlfn.TEXTJOIN(" | ",TRUE,"Total: "&COUNTIF(H36:AD36,"Q*")+COUNTIF(H36:AD36,"Ideation")+COUNTIF(H36:AD36,"Done")+COUNTIF(H36:AD36,"Run"),"Ideation: "&COUNTIF(H36:AD36,"Ideation"),"Pilot: "&COUNTIF(H36:AD36,"*Pilot"),"Scale: "&COUNTIF(H36:AD36,"*Scale"),"Run: "&COUNTIF(H36:AD36,"Run"),"Done: "&COUNTIF(H36:AD36,"Done")) -> Total: 7 | Ideation: 1 | Pilot: 5 | Scale: 1 | Run: 0 | Done: 0 | K36: Q2-Pilot | N36: Q2-Pilot | P36: Q2-Pilot | U36: Q2-Pilot | X36: Ideation | AB36: Q2-Pilot | AC36: Q2-Scale
B37: Marketing | C37: BB | D37: Qia CHEN | E37: Marketing Mix Modeling | G37: =_xlfn.TEXTJOIN(" | ",TRUE,"Total: "&COUNTIF(H37:AD37,"Q*")+COUNTIF(H37:AD37,"Ideation")+COUNTIF(H37:AD37,"Done")+COUNTIF(H37:AD37,"Run"),"Ideation: "&COUNTIF(H37:AD37,"Ideation"),"Pilot: "&COUNTIF(H37:AD37,"*Pilot"),"Scale: "&COUNTIF(H37:AD37,"*Scale"),"Run: "&COUNTIF(H37:AD37,"Run"),"Done: "&COUNTIF(H37:AD37,"Done")) -> Total: 2 | Ideation: 1 | Pilot: 1 | Scale: 0 | Run: 0 | Done: 0 | Z37: Q4-Pilot | AA37: Ideation
B38: Marketing | C38: QW | D38: Yuanne CHANG | E38: GEO | G38: =_xlfn.TEXTJOIN(" | ",TRUE,"Total: "&COUNTIF(H38:AD38,"Q*")+COUNTIF(H38:AD38,"Ideation")+COUNTIF(H38:AD38,"Done")+COUNTIF(H38:AD38,"Run"),"Ideation: "&COUNTIF(H38:AD38,"Ideation"),"Pilot: "&COUNTIF(H38:AD38,"*Pilot"),"Scale: "&COUNTIF(H38:AD38,"*Scale"),"Run: "&COUNTIF(H38:AD38,"Run"),"Done: "&COUNTIF(H38:AD38,"Done")) -> Total: 15 | Ideation: 7 | Pilot: 8 | Scale: 0 | Run: 0 | Done: 0 | H38: Ideation | I38: Ideation | J38: Q4-Pilot | K38: Q3-Pilot | L38: Q4-Pilot | M38: Q3-Pilot | R38: Q4-Pilot | S38: Ideation | T38: Q3-Pilot | U38: Ideation | X38: Ideation | Y38: Ideation | Z38: Ideation | AA38: Q3-Pilot | AC38: Q4-Pilot
B39: Marketing | C39: QW | D39: Yuanne CHANG | E39: Actionable Insights | G39: =_xlfn.TEXTJOIN(" | ",TRUE,"Total: "&COUNTIF(H39:AD39,"Q*")+COUNTIF(H39:AD39,"Ideation")+COUNTIF(H39:AD39,"Done")+COUNTIF(H39:AD39,"Run"),"Ideation: "&COUNTIF(H39:AD39,"Ideation"),"Pilot: "&COUNTIF(H39:AD39,"*Pilot"),"Scale: "&COUNTIF(H39:AD39,"*Scale"),"Run: "&COUNTIF(H39:AD39,"Run"),"Done: "&COUNTIF(H39:AD39,"Done")) -> Total: 5 | Ideation: 4 | Pilot: 1 | Scale: 0 | Run: 0 | Done: 0 | I39: Ideation | J39: Ideation | L39: Ideation | M39: Q3-Pilot | T39: Ideation
B40: Marketing | C40: QW | D40: Yuanne CHANG | E40: Enhanced Targeting | G40: =_xlfn.TEXTJOIN(" | ",TRUE,"Total: "&COUNTIF(H40:AD40,"Q*")+COUNTIF(H40:AD40,"Ideation")+COUNTIF(H40:AD40,"Done")+COUNTIF(H40:AD40,"Run"),"Ideation: "&COUNTIF(H40:AD40,"Ideation"),"Pilot: "&COUNTIF(H40:AD40,"*Pilot"),"Scale: "&COUNTIF(H40:AD40,"*Scale"),"Run: "&COUNTIF(H40:AD40,"Run"),"Done: "&COUNTIF(H40:AD40,"Done")) -> Total: 4 | Ideation: 3 | Pilot: 1 | Scale: 0 | Run: 0 | Done: 0 | I40: Ideation | J40: Ideation | M40: Q3-Pilot | T40: Ideation

Sheet Todo
A1: 1. 组织架构图 （Digital，CRM，Global）
A2: 2. 核心业务目标
A3: 3. AI transformation roadmap
A4: 4. 当存在付费项目合作，展开描述，有visibility
A6: 该工作整理的目的是可以快速看到卡点
A8: 每两周更新项目log

Sheet B26 Stats
B2: Maison | C2: Louis Vuitton | D2: Christine Dior Couture | E2: Loro Piana | F2: Fendi | G2: Celine | H2: Loewe | I2: Givenchy | J2: Kenzo | K2: Berluti | L2: Marc Jocobs | M2: Rimowa | N2: Tiffany | O2: Bvlgari | P2: Chaumet | Q2: Fred | R2: Hublot | S2: TAG Heuer | T2: Zenith | U2: Perfume Christine Dior | V2: Guerlain | W2: Beauty Division (Givenchy,Kenzo, Loewe, Benefit, Makeup forever, ADP, Fresh) | X2: Sephora
B3: Owner | C3: Rachael JIANG | D3: Mars YU | E3: Rachael JIANG | F3: Wendy CHEN | G3: Livia GAO | H3: Chen JIA | I3: Xintong YAN | J3: Chen JIA | K3: Yuanne CHANG | L3: Chen JIA | M3: Wendy CHEN | N3: Candy HOU | O3: Chenlong WANG | P3: Qiwen MO | Q3: Rikka CHEN | R3: Wendy CHEN | S3: Qiwen MO | T3: Qiwen MO | U3: Chenlong WANG | V3: Candy HOU | W3: Wendy CHEN | X3: Qia CHEN
B4: Digital project budget change vs. B25 | C4: 根据sales target调整，保留同样的比例 | E4: budget on par with EC target - proportion | F4: 持平 | K4: 不比去年多，可能R1还要砍 | M4: 持平 | N4: R1砍了 | O4: 降低 | P4: 基本持平 | Q4: 有涨幅 | U4: 略涨 | W4: R1砍了 | X4: 待5月中确认
B5: EC project budget change vs. B25 | E5: flat | F5: 持平 | I5: 持平 | K5: 不比去年多，可能R1还要砍 | M5: 持平 | O5: 持平 | P5: 基本持平 | Q5: 基本持平 | U5: 持平 | X5: 待5月中确认
B6: AI project budget change vs. B25 | E6: tbc | F6: 没有特别预留 | K6: 没有特别预留 | M6: 待讨论 | N6: R1砍了 | O6: 略涨 | P6: 和去年一样 | Q6: 增长 | U6: 持平 | X6: 有预留
B7: AI project planning | E7: tbc | F7: 没有特别预留 | K7: Enrich & 针对AIGC 相关（例如try-on) 的感兴趣 | M7: 待讨论 | O7: 已明确 | P7: contextual outreach | Q7: 和Mars对了High potential的AI项目，Enrich也会上auto journey | U7: 无 | X7: 有预留
B8: EC growth rate target | C8: 4% after R1 | E8: revised after R1 to 18% | F8: Target +15% | I8: 与去年一样，预算很少 | K8: 15% ， mostly on Tmall | M8: Target +25% | O8: 无 | P8: low single digit | Q8: Single digit growth | U8: 无 | X8: 待定

Sheet Maison>

Sheet Louis Vuitton
A1: Back <-
B2: ='Maison Dimension Tracking Table'!H2 -> Louis Vuitton
B4: ='Maison Dimension Tracking Table'!H7 -> Rachael JIANG | C4: ='Maison Dimension Tracking Table'!H3 -> Total: 7
B7: LV x Group Prospective Joint Projects | C7: Owner | D7: Status | E7: Remark | F7: LV in-house Projects | G7: Status | H7: Remark
B8: {=_xlfn._xlws.FILTER('Maison Dimension Tracking Table'!E8:E40,'Maison Dimension Tracking Table'!H8:H40<>"")} -> 【Clienteling】Gen AI Client Knowledge | C8: {=_xlfn._xlws.FILTER('Maison Dimension Tracking Table'!D8:D40,'Maison Dimension Tracking Table'!H8:H40<>"")} -> Chenlong WANG | D8: {=_xlfn._xlws.FILTER('Maison Dimension Tracking Table'!H8:H40,'Maison Dimension Tracking Table'!H8:H40<>"")} -> Ideation | E8: Maison Tech | F8: 【Gen AI for Omni】Gaston Order Agent | G8: Build | H8: Maison Tech
B9: State of Data（June） | C9: Mars YU | D9: Done | F9: 【Gen AI for Omni】Atlas Internal SOP | G9: Build | H9: Maison Tech
B10: 【Marketing Automation 】Personalized journeys through QA migration, upgrades, and orchestration | C10: Qiwen MO | D10: Q3-Pilot | E10: Maison Tech | F10: 【Gen AI for SupplyChain&Logistics】LV Care Repair Policy QA | G10: Framing | H10: Maison Tech
B11: 【Clienteling】Gen AI Contextual Outreach | C11: Candy HOU | D11: Ideation | F11: 【Gen AI for SupplyChain&Logistics】HS Code | G11: Design | H11: Maison Tech
B12: 【Client Community】CRM upskilling and community | C12: Candy HOU | D12: Done | F12: 【Gen AI for Merch】Market Trend Analysis | G12: Framing | H12: Maison Tech
B13: 【Clienteling】WeCom tools benchmark and feature innovation | C13: Qiwen MO | D13: Done | F13: 【Gen AI for Finance】Gaston for Finance-SOP and Q&A | G13: Framing | H13: Maison Tech
B14: China AI omni landscape strategy playbook 2) Agentic commerce | C14: Wendy CHEN | D14: Ideation | F14: 【Gen AI for Legal】Maia for Legal | G14: Test | H14: Maison Tech
B15: Al for omni excellence - 3) Smart Search | C15: Wendy CHEN | D15: Q3-Pilot | F15: 【Gen AI for HR】Gaston for Employee HR SOP and Q&A | G15: Framing | H15: Maison Tech
B16: Omni incentive orchestration | C16: Rikka CHEN | D16: Run
B17: VoC (NPS) | C17: Rikka CHEN | D17: Run
B18: Al training for omni-retail | C18: Rikka CHEN | D18: Q4-Scale
B19: Gen-AI CSC | C19: Qia CHEN | D19: Run
B20: GEO | C20: Yuanne CHANG | D20: Ideation

Sheet Christine Dior Couture
A1: Back <-
B2: ='Maison Dimension Tracking Table'!I2 -> Christine Dior Couture
B4: ='Maison Dimension Tracking Table'!I7 -> Mars YU | C4: ='Maison Dimension Tracking Table'!I3 -> Total: 8
B7: CDC x Group Prospective Joint Projects Projects | C7: Owner | D7: Status | E7: Remark
B8: {=_xlfn._xlws.FILTER('Maison Dimension Tracking Table'!E8:E40,'Maison Dimension Tracking Table'!I8:I40<>"")} -> Enrich project scaling | C8: {=_xlfn._xlws.FILTER('Maison Dimension Tracking Table'!D8:D40,'Maison Dimension Tracking Table'!I8:I40<>"")} -> Mars YU | D8: {=_xlfn._xlws.FILTER('Maison Dimension Tracking Table'!I8:I40,'Maison Dimension Tracking Table'!I8:I40<>"")} -> Ideation
B9: 【Clienteling】Gen AI Client Knowledge | C9: Chenlong WANG | D9: Q4-Pilot
B10: State of Data（June） | C10: Mars YU | D10: Done
B11: 【Marketing Automation 】Personalized journeys through QA migration, upgrades, and orchestration | C11: Qiwen MO | D11: Q1-Scale
B12: 【Clienteling】Gen AI Contextual Outreach | C12: Candy HOU | D12: Q4-Pilot
B13: 【Client Community】CRM upskilling and community | C13: Candy HOU | D13: Done
B14: 【Clienteling】WeCom tools benchmark and feature innovation | C14: Qiwen MO | D14: Done
B15: Al for omni excellence - 3) Smart Search | C15: Wendy CHEN | D15: Run
B16: VoC (NPS) | C16: Rikka CHEN | D16: Run
B17: Gen-AI CSC | C17: Qia CHEN | D17: Q3-Scale
B18: GEO | C18: Yuanne CHANG | D18: Ideation
B19: Actionable Insights | C19: Yuanne CHANG | D19: Ideation
B20: Enhanced Targeting | C20: Yuanne CHANG | D20: Ideation

Sheet Loro Piana
A1: Back <-
B2: ='Maison Dimension Tracking Table'!J2 -> Loro Piana
B4: ='Maison Dimension Tracking Table'!J7 -> Rachael JIANG | C4: ='Maison Dimension Tracking Table'!J3 -> Total: 8
B7: Projects | C7: Owner | D7: Status | F7: Maison name
B8: {=_xlfn._xlws.FILTER('Maison Dimension Tracking Table'!E8:E40,'Maison Dimension Tracking Table'!J8:J40<>"")} -> Enrich project scaling | C8: {=_xlfn._xlws.FILTER('Maison Dimension Tracking Table'!D8:D40,'Maison Dimension Tracking Table'!J8:J40<>"")} -> Mars YU | D8: {=_xlfn._xlws.FILTER('Maison Dimension Tracking Table'!J8:J40,'Maison Dimension Tracking Table'!J8:J40<>"")} -> Run
B9: 【Advanced Journey 】High potential one-timer/repeater | C9: Chenlong WANG | D9: Run
B10: 【Advanced Journey 】Product Recom DREAM 2.0 | C10: Chenlong WANG | D10: Ideation | E10: Q1 2027 | F10: Product recommendation - 27Q1
B11: 【Clienteling】Gen AI Client Knowledge | C11: Chenlong WANG | D11: Ideation | F11: Client summary + advanced search - 27 Q2
B12: State of Data（June） | C12: Mars YU | D12: Done
B13: 【Marketing Automation 】Personalized journeys through QA migration, upgrades, and orchestration | C13: Qiwen MO | D13: Q1-Scale
B14: 【Client Community】CRM upskilling and community | C14: Candy HOU | D14: Done
B15: 【Clienteling】WeCom tools benchmark and feature innovation | C15: Qiwen MO | D15: Done
B16: China AI omni landscape strategy playbook 1) Drive to Store | C16: Wendy CHEN | D16: Q4-Pilot | F16: Recruitment for new & Traffic acquisition +GEO
B17: Al for omni excellence - 1) Tracking Lab | C17: Wendy CHEN | D17: Run
B18: Al for omni excellence - 3) Smart Search | C18: Wendy CHEN | D18: Ideation | F18: Picture search for EC - 27Q1
B19: VoC (NPS) | C19: Rikka CHEN | D19: Run
B20: GEO | C20: Yuanne CHANG | D20: Q4-Pilot | F20: Recruitment for new & Traffic acquisition +GEO
B21: Actionable Insights | C21: Yuanne CHANG | D21: Ideation
B22: Enhanced Targeting | C22: Yuanne CHANG | D22: Ideation
F24: Knowledge POT (LP HQ use case) - retail knowledge 27 Q2

Sheet Fendi
A1: Back <-
B2: ='Maison Dimension Tracking Table'!K2 -> Fendi
B4: ='Maison Dimension Tracking Table'!K7 -> Wendy CHEN | C4: ='Maison Dimension Tracking Table'!K3 -> Total: 8
B7: Projects | C7: Owner | D7: Status
B8: {=_xlfn._xlws.FILTER('Maison Dimension Tracking Table'!E8:E40,'Maison Dimension Tracking Table'!K8:K40<>"")} -> Enrich project scaling | C8: {=_xlfn._xlws.FILTER('Maison Dimension Tracking Table'!D8:D40,'Maison Dimension Tracking Table'!K8:K40<>"")} -> Mars YU | D8: {=_xlfn._xlws.FILTER('Maison Dimension Tracking Table'!K8:K40,'Maison Dimension Tracking Table'!K8:K40<>"")} -> Run
B9: 【Advanced Journey 】High potential one-timer/repeater | C9: Chenlong WANG | D9: Run
B10: State of Data（June） | C10: Mars YU | D10: Done
B11: 【Marketing Automation 】Personalized journeys through QA migration, upgrades, and orchestration | C11: Qiwen MO | D11: Q2-Scale
B12: 【Client Community】CRM upskilling and community | C12: Candy HOU | D12: Done
B13: 【Clienteling】WeCom tools benchmark and feature innovation | C13: Qiwen MO | D13: Done
B14: China AI omni landscape strategy playbook 2) Agentic commerce | C14: Wendy CHEN | D14: Q3-Pilot
B15: Al for omni excellence - 2) Product recommendation | C15: Wendy CHEN | D15: Ideation | H15: Back <-
B16: Al for omni excellence - 3) Smart Search | C16: Wendy CHEN | D16: Ideation
B17: Al training for omni-retail | C17: Rikka CHEN | D17: Q2-Pilot
B18: 【Gen AI Content Hub】Asset Production & Distribution | C18: Qia CHEN | D18: Ideation
B19: 【Gen AI Content Hub】Asset Production & Distribution - LucIA | C19: Qia CHEN | D19: Q2-Pilot
B20: GEO | C20: Yuanne CHANG | D20: Q3-Pilot
B60: High potential repeater - 2026 Q3
B61: ENRICH X FUR 2026 Q3
B62: Product recommendation - 2026 Q3/Q4
B63: NPS (NPS depends on global)
B64: AI Training to check with Rikka on the pilot results
B65: Gen AI Contents/Lucia check with Rachael

Sheet Celine
A1: Back <-
B2: ='Maison Dimension Tracking Table'!L2 -> Celine
B4: ='Maison Dimension Tracking Table'!L7 -> Livia GAO | C4: ='Maison Dimension Tracking Table'!L3 -> Total: 11
B7: Projects | C7: Owner | D7: Status
B8: {=_xlfn._xlws.FILTER('Maison Dimension Tracking Table'!E8:E40,'Maison Dimension Tracking Table'!L8:L40<>"")} -> Enrich project scaling | C8: {=_xlfn._xlws.FILTER('Maison Dimension Tracking Table'!D8:D40,'Maison Dimension Tracking Table'!L8:L40<>"")} -> Mars YU | D8: {=_xlfn._xlws.FILTER('Maison Dimension Tracking Table'!L8:L40,'Maison Dimension Tracking Table'!L8:L40<>"")} -> Run
B9: 【Advanced Journey 】High potential one-timer/repeater | C9: Chenlong WANG | D9: Run
B10: 【Advanced Journey 】Product Recom DREAM 2.0 | C10: Chenlong WANG | D10: Q4-Pilot
B11: 【Advanced Journey 】Total-look recommendation | C11: Livia GAO | D11: Ideation
B12: State of Data（June） | C12: Mars YU | D12: Done
B13: 【Marketing Automation 】Personalized journeys through QA migration, upgrades, and orchestration | C13: Qiwen MO | D13: Q3-Pilot
B14: 【Clienteling】Gen AI Contextual Outreach | C14: Candy HOU | D14: Ideation
B15: 【Client Community】CRM upskilling and community | C15: Candy HOU | D15: Done
B16: 【Clienteling】WeCom tools benchmark and feature innovation | C16: Qiwen MO | D16: Done
B17: 【KOS】AI solutions (scanning, content assistant, task management ) | C17: TBD | D17: Ideation
B18: Al for omni excellence - 1) Tracking Lab | C18: Wendy CHEN | D18: Q2-Scale
B19: Al for omni excellence - 2) Product recommendation | C19: Wendy CHEN | D19: Q4-Pilot
B20: Al for omni excellence - 3) Smart Search | C20: Wendy CHEN | D20: Ideation
... B23: Actionable Insights | C23: Yuanne CHANG | D23: Ideation

Sheet Loewe
A1: Back <-
B2: ='Maison Dimension Tracking Table'!M2 -> Loewe
A4: KA | B4: ='Maison Dimension Tracking Table'!M7 -> Yuanne CHANG | C4: ='Maison Dimension Tracking Table'!M3 -> Total: 13
A5: Champion | B5: Florian MULLER
B7: Projects | C7: Owner | D7: Status
B8: {=_xlfn._xlws.FILTER('Maison Dimension Tracking Table'!E8:E40,'Maison Dimension Tracking Table'!M8:M40<>"")} -> Enrich project scaling | C8: {=_xlfn._xlws.FILTER('Maison Dimension Tracking Table'!D8:D40,'Maison Dimension Tracking Table'!M8:M40<>"")} -> Mars YU | D8: {=_xlfn._xlws.FILTER('Maison Dimension Tracking Table'!M8:M40,'Maison Dimension Tracking Table'!M8:M40<>"")} -> Run
B9: 【Advanced Journey 】High potential one-timer/repeater | C9: Chenlong WANG | D9: Run
B10: 【Advanced Journey 】High potential VIC detection | C10: Chenlong WANG | D10: Q3-Scale
B11: 【Advanced Journey 】Product Recom DREAM 2.0 | C11: Chenlong WANG | D11: Q4-Pilot
B12: 【Advanced Journey 】Total-look recommendation | C12: Livia GAO | D12: Q4-Pilot
B13: State of Data（June） | C13: Mars YU | D13: Done
B14: 【Marketing Automation 】Personalized journeys through QA migration, upgrades, and orchestration | C14: Qiwen MO | D14: Q4-Pilot
B15: 【Client Community】CRM upskilling and community | C15: Candy HOU | D15: Done
B16: 【Clienteling】WeCom tools benchmark and feature innovation | C16: Qiwen MO | D16: Done
B17: 【KOS】AI solutions (scanning, content assistant, task management ) | C17: TBD | D17: Ideation
B18: China AI omni landscape strategy playbook 2) Agentic commerce | C18: Wendy CHEN | D18: Ideation
B19: Al for omni excellence - 1) Tracking Lab | C19: Wendy CHEN | D19: Ideation
B20: Al for omni excellence - 2) Product recommendation | C20: Wendy CHEN | D20: Q4-Pilot
B21: VoC (NPS) | C21: Rikka CHEN | D21: Q4-Scale
B22: Al training for omni-retail | C22: Rikka CHEN | D22: Ideation | E22: early 2027
B23: GEO | C23: Yuanne CHANG | D23: Q3-Pilot
B24: Actionable Insights | C24: Yuanne CHANG | D24: Q3-Pilot
B25: Enhanced Targeting | C25: Yuanne CHANG | D25: Q3-Pilot

Sheet Givenchy
A1: Back <-
B2: ='Maison Dimension Tracking Table'!N2 -> Givenchy
B4: ='Maison Dimension Tracking Table'!N7 -> Xintong YAN | C4: ='Maison Dimension Tracking Table'!N3 -> Total: 3
B7: Projects | C7: Owner | D7: Status
B8: {=_xlfn._xlws.FILTER('Maison Dimension Tracking Table'!E8:E40,'Maison Dimension Tracking Table'!N8:N40<>"")} -> 【Advanced Journey 】High potential propensity for collection | C8: {=_xlfn._xlws.FILTER('Maison Dimension Tracking Table'!D8:D40,'Maison Dimension Tracking Table'!N8:N40<>"")} -> Chenlong WANG | D8: {=_xlfn._xlws.FILTER('Maison Dimension Tracking Table'!N8:N40,'Maison Dimension Tracking Table'!N8:N40<>"")} -> Done
B9: 【Marketing Automation 】Personalized journeys through QA migration, upgrades, and orchestration | C9: Qiwen MO | D9: Q4-Pilot
B10: China AI omni landscape strategy playbook 2) Agentic commerce | C10: Wendy CHEN | D10: Ideation
B11: 【Gen AI Content Hub】Asset Production & Distribution | C11: Qia CHEN | D11: Run
B12: 【Gen AI Content Hub】Asset Production & Distribution - LucIA | C12: Qia CHEN | D12: Q2-Pilot
E62: Head of EC for | G62: 【Gen AI Content Hub】Asset Production & Distribution | Q62: 【Marketing Automation 】Personalized journeys through QA migration, upgrades, and orchestration | Y62: Head of Client Development for DS related project (early adopters)
B86: AI Future Planning
B88: Top priority: Atom上线，目前aim今年，否则其他的项目都会受限于Atom
B89: 1-New adopter（4月份在做的） + 新客复购（6-7月想做新一次客的模型）
B90: 2-Marketing automation - 还在聊，今年在做到什么程度，部署基础的task
B91: 3-Contextual outreach有需求，但要等MA的完成，没有Atom是痛点
B92: 4-需求：new one-timers 与 enrich结合 就会有提升，有没有可能撞一下enrich的池子
B93: 5-想做VIC的潜在发掘，新的top的客人（更有兴趣）
B94: 6-产品推荐有兴趣

Sheet Kenzo
A1: Back <-
B2: ='Maison Dimension Tracking Table'!O2 -> Kenzo
B4: ='Maison Dimension Tracking Table'!O7 -> TBD | C4: ='Maison Dimension Tracking Table'!O3 -> Total: 0
B7: Projects | C7: Owner | D7: Status
B8: {=_xlfn._xlws.FILTER('Maison Dimension Tracking Table'!E8:E40,'Maison Dimension Tracking Table'!O8:O40<>"")} -> 【Client Community】CRM upskilling and community | C8: {=_xlfn._xlws.FILTER('Maison Dimension Tracking Table'!D8:D40,'Maison Dimension Tracking Table'!O8:O40<>"")} -> Candy HOU | D8: {=_xlfn._xlws.FILTER('Maison Dimension Tracking Table'!N8:N40,'Maison Dimension Tracking Table'!O8:O40<>"")} -> 0

Sheet Berluti
A1: Back <-
B2: ='Maison Dimension Tracking Table'!P2 -> Berluti
B4: ='Maison Dimension Tracking Table'!P7 -> Yuanne CHANG | C4: ='Maison Dimension Tracking Table'!P3 -> Total: 3
B7: Projects | C7: Owner | D7: Status
B8: {=_xlfn._xlws.FILTER('Maison Dimension Tracking Table'!E8:E40,'Maison Dimension Tracking Table'!P8:P40<>"")} -> Enrich project scaling | C8: {=_xlfn._xlws.FILTER('Maison Dimension Tracking Table'!D8:D40,'Maison Dimension Tracking Table'!P8:P40<>"")} -> Mars YU | D8: {=_xlfn._xlws.FILTER('Maison Dimension Tracking Table'!P8:P40,'Maison Dimension Tracking Table'!P8:P40<>"")} -> Q2-Pilot
B9: 【Client Community】CRM upskilling and community | C9: Candy HOU | D9: Done
B10: 【Clienteling】WeCom tools benchmark and feature innovation | C10: Qiwen MO | D10: Done
B11: 【Gen AI Content Hub】Asset Production & Distribution | C11: Qia CHEN | D11: Ideation
B12: 【Gen AI Content Hub】Asset Production & Distribution - LucIA | C12: Qia CHEN | D12: Q2-Pilot
B14: Berluti 2026 Strategy
B15: Internal Recruitment - Product Cross-selling
B17: Challenges
B18: Cross-sell but some offline stores have limited products (AI try-on）
B19: Offline traffic limited （Enrich - but difficulty with driving consent rate）
B22: Berluti Org Chart with Key Contacts (regarding China affairs)
B48: *Olivia involved with Clienteling and Retail

Sheet Marc Jocobs
A1: Back <-
B2: ='Maison Dimension Tracking Table'!Q2 -> Marc Jocobs
B4: ='Maison Dimension Tracking Table'!Q7 -> TBD | C4: ='Maison Dimension Tracking Table'!Q3 -> Total: 0
B7: Projects | C7: Owner | D7: Status
B8: {=_xlfn._xlws.FILTER('Maison Dimension Tracking Table'!E8:E40,'Maison Dimension Tracking Table'!Q8:Q40<>"")} -> #VALUE! | C8: {=_xlfn._xlws.FILTER('Maison Dimension Tracking Table'!D8:D40,'Maison Dimension Tracking Table'!Q8:Q40<>"")} -> #VALUE! | D8: {=_xlfn._xlws.FILTER('Maison Dimension Tracking Table'!Q8:Q40,'Maison Dimension Tracking Table'!Q8:Q40<>"")} -> #VALUE!

Sheet Rimowa
A1: Back <-
B2: ='Maison Dimension Tracking Table'!R2 -> Rimowa
B4: ='Maison Dimension Tracking Table'!R7 -> Wendy CHEN | C4: ='Maison Dimension Tracking Table'!R3 -> Total: 7
B7: Projects | C7: Owner | D7: Status
B8: {=_xlfn._xlws.FILTER('Maison Dimension Tracking Table'!E8:E40,'Maison Dimension Tracking Table'!R8:R40<>"")} -> Enrich project scaling | C8: {=_xlfn._xlws.FILTER('Maison Dimension Tracking Table'!D8:D40,'Maison Dimension Tracking Table'!R8:R40<>"")} -> Mars YU | D8: {=_xlfn._xlws.FILTER('Maison Dimension Tracking Table'!R8:R40,'Maison Dimension Tracking Table'!R8:R40<>"")} -> Ideation
B9: 【Clienteling】Gen AI Contextual Outreach | C9: Candy HOU | D9: Ideation
B10: 【Client Community】CRM upskilling and community | C10: Candy HOU | D10: Done
B11: 【Clienteling】WeCom tools benchmark and feature innovation | C11: Qiwen MO | D11: Done
B12: China AI omni landscape strategy playbook 2) Agentic commerce | C12: Wendy CHEN | D12: Q4-Pilot
B13: Al for omni excellence - 2) Product recommendation | C13: Wendy CHEN | D13: Ideation
B14: Al for omni excellence - 3) Smart Search | C14: Wendy CHEN | D14: Ideation
B15: VoC (NPS) | C15: Rikka CHEN | D15: Run
B16: Al training for omni-retail | C16: Rikka CHEN | D16: Q4-Pilot
B17: GEO | C17: Yuanne CHANG | D17: Q4-Pilot

Sheet Tiffany
A1: Back <-
B2: ='Maison Dimension Tracking Table'!S2 -> Tiffany
B4: ='Maison Dimension Tracking Table'!S7 -> Candy HOU | C4: ='Maison Dimension Tracking Table'!S3 -> Total: 10
B7: Projects | C7: Owner | D7: Status | E7: Remarks
B8: {=_xlfn._xlws.FILTER('Maison Dimension Tracking Table'!E8:E40,'Maison Dimension Tracking Table'!S8:S40<>"")} -> Enrich project scaling | C8: {=_xlfn._xlws.FILTER('Maison Dimension Tracking Table'!D8:D40,'Maison Dimension Tracking Table'!S8:S40<>"")} -> Mars YU | D8: {=_xlfn._xlws.FILTER('Maison Dimension Tracking Table'!S8:S40,'Maison Dimension Tracking Table'!S8:S40<>"")} -> Run
B9: 【Advanced Journey 】High potential one-timer/repeater | C9: Chenlong WANG | D9: Run | E9: Pending Bulgari result
B10: 【Advanced Journey 】High potential propensity for collection | C10: Chenlong WANG | D10: Ideation | E10: 2027
B11: 【Clienteling】Gen AI Client Knowledge | C11: Chenlong WANG | D11: Ideation
B12: State of Data（June） | C12: Mars YU | D12: Done
B13: 【Marketing Automation 】Personalized journeys through QA migration, upgrades, and orchestration | C13: Qiwen MO | D13: Q3-Scale
B14: 【Gen AI Content Hub】Content Tagging & Distrubution | C14: Qiwen MO | D14: Q2-Scale
B15: 【Clienteling】Gen AI Contextual Outreach | C15: Candy HOU | D15: Q3-Scale
B16: 【Client Community】CRM upskilling and community | C16: Candy HOU | D16: Done
B17: 【Clienteling】WeCom tools benchmark and feature innovation | C17: Qiwen MO | D17: Done | E17: 2028
B18: 【KOS】AI solutions (scanning, content assistant, task management ) | C18: TBD | D18: Q1-Scale | E18: 2026 2H
B19: China AI omni landscape strategy playbook 2) Agentic commerce | C19: Wendy CHEN | D19: Ideation
B20: VoC (NPS) | C20: Rikka CHEN | D20: Run | E20: 2027
B21: Al training for omni-retail | C21: Rikka CHEN | D21: Ideation
B22: Gen-AI CSC | C22: Qia CHEN | D22: Ideation | E22: Limited edition, HJ
B23: 【Gen AI Content Hub】Asset Production & Distribution | C23: Qia CHEN | D23: Run
B24: GEO | C24: Yuanne CHANG | D24: Ideation

Sheet Bvlgari
A1: Back <-
B2: ='Maison Dimension Tracking Table'!T2 -> Bvlgari
B4: ='Maison Dimension Tracking Table'!T7 -> Chenlong WANG | C4: ='Maison Dimension Tracking Table'!T3 -> Total: 14
B5: AI Champion： Ryan XIE ｜ Maggie ZHU，Charles LIU，Kelsey GU
B7: Projects | C7: Owner | D7: Status
B8: {=_xlfn._xlws.FILTER('Maison Dimension Tracking Table'!E8:E40,'Maison Dimension Tracking Table'!T8:T40<>"")} -> Enrich project scaling | C8: {=_xlfn._xlws.FILTER('Maison Dimension Tracking Table'!D8:D40,'Maison Dimension Tracking Table'!T8:T40<>"")} -> Mars YU | D8: {=_xlfn._xlws.FILTER('Maison Dimension Tracking Table'!T8:T40,'Maison Dimension Tracking Table'!T8:T40<>"")} -> Run
B9: 【Advanced Journey 】High potential one-timer/repeater | C9: Chenlong WANG | D9: Run
B10: 【Advanced Journey 】High potential client list orchestration | C10: Xintong YAN | D10: Q3-Pilot
B11: 【Advanced Journey 】High potential propensity for collection | C11: Chenlong WANG | D11: Run
B12: 【Advanced Journey 】Product Recom DREAM 2.0 | C12: Chenlong WANG | D12: Q2-Pilot
B13: 【Clienteling】Gen AI Client Knowledge | C13: Chenlong WANG | D13: Q4-Pilot
B14: State of Data（June） | C14: Mars YU | D14: Done
B15: 【Marketing Automation 】Personalized journeys through QA migration, upgrades, and orchestration | C15: Qiwen MO | D15: Q1-Scale
B16: 【Gen AI Content Hub】Content Tagging & Distrubution | C16: Qiwen MO | D16: Q2-Pilot
B17: 【Clienteling】Gen AI Contextual Outreach | C17: Candy HOU | D17: Q2-Pilot
B18: 【Client Community】CRM upskilling and community | C18: Candy HOU | D18: Done
B19: 【Clienteling】WeCom tools benchmark and feature innovation | C19: Qiwen MO | D19: Done
B20: China AI omni landscape strategy playbook 1) Drive to Store | C20: Wendy CHEN | D20: Ideation
... B28: Enhanced Targeting | C28: Yuanne CHANG | D28: Ideation
B30: Personalized PDP
B87: Meeting AI Road Map | C87: 46151
B89: Maggie, Kelsey, Charles, Ryan
B91: 1. PDP 的内容能不能借鉴contextual outreach的结果做成个性化的展示页面
B92: 2. 平台很多标签拿不回来，帮着别人在做私域运营
B93: 3. AI Orchestr 如何做评价，目前global得名单6个月刷一次，我们已经更新到一个月一刷，效果怎么动态评价
B94: 4. content 不止3D建模，投放内容也是SKY帮着做的，global会做这部分content的validation
B96: 大的方向希望能够合在一起看，从omni-retail的角度做，而不分开
B97: 之前的项目已经做了很多，不能一直Pilot，要考虑如何做Scale up
B98: 整个scale up的过程要考虑有机的结合起来，客人也是非常复合的，需要赋能各个部分
B99: GEO会今年做起来
B124: https://lvmh-my.sharepoint.com/:p:/r/personal/chenlong_wang_lvmh_com/Documents/work/Team%20work/China%20Digital%20Sharing_Bvlgari%20Workshop.pptx?d=wa58577e9019446f49e8e32292b9b5705&e=4%3aa188bdc218c14caf85353ad6758eb3ab&sharingv2=true&fromShare=true&at=9

Sheet Chaumet
A1: Back <-
B2: ='Maison Dimension Tracking Table'!U2 -> Chaumet
B4: ='Maison Dimension Tracking Table'!U7 -> Qiwen MO | C4: ='Maison Dimension Tracking Table'!U3 -> Total: 9
B5: Amy WU
B7: Projects | C7: Owner | D7: Status
B8: {=_xlfn._xlws.FILTER('Maison Dimension Tracking Table'!E8:E40,'Maison Dimension Tracking Table'!U8:U40<>"")} -> Enrich project scaling | C8: {=_xlfn._xlws.FILTER('Maison Dimension Tracking Table'!D8:D40,'Maison Dimension Tracking Table'!U8:U40<>"")} -> Mars YU | D8: {=_xlfn._xlws.FILTER('Maison Dimension Tracking Table'!U8:U40,'Maison Dimension Tracking Table'!U8:U40<>"")} -> Run
B9: 【Advanced Journey 】High potential one-timer/repeater | C9: Chenlong WANG | D9: Run
B10: 【Advanced Journey 】High potential propensity for collection | C10: Chenlong WANG | D10: Run
B11: 【Advanced Journey 】Product Recom DREAM 2.0 | C11: Chenlong WANG | D11: Ideation
B12: State of Data（June） | C12: Mars YU | D12: Done
B13: 【Marketing Automation 】Personalized journeys through QA migration, upgrades, and orchestration | C13: Qiwen MO | D13: Q3-Scale
B14: 【Gen AI Content Hub】Content Tagging & Distrubution | C14: Qiwen MO | D14: Q3-Pilot
B15: 【Clienteling】Gen AI Contextual Outreach | C15: Candy HOU | D15: Q3-Pilot
B16: 【Client Community】CRM upskilling and community | C16: Candy HOU | D16: Done
B17: 【Clienteling】WeCom tools benchmark and feature innovation | C17: Qiwen MO | D17: Done
B18: 【KOS】AI solutions (scanning, content assistant, task management ) | C18: TBD | D18: Ideation
B19: China AI omni landscape strategy playbook 2) Agentic commerce | C19: Wendy CHEN | D19: Ideation | F19: *solution introduced to CRM head, interested in GenAI for 1v1 clienteling, e.g. on-model try-on, need alignment with MD and Janet& Rachael's endorsement during the global visit (May 2026)
B20: Al for omni excellence - 1) Tracking Lab | C20: Wendy CHEN | D20: Run
B21: VoC (NPS) | C21: Rikka CHEN | D21: Run
B22: 【Gen AI Content Hub】Asset Production & Distribution | C22: Qia CHEN | D22: Ideation
B23: 【Gen AI Content Hub】Asset Production & Distribution - LucIA | C23: Qia CHEN | D23: Q2-Pilot
B24: GEO | C24: Yuanne CHANG | D24: Ideation

Sheet Fred
A1: Back <-
B2: ='Maison Dimension Tracking Table'!V2 -> Fred
B4: ='Maison Dimension Tracking Table'!V7 -> Rikka CHEN | C4: ='Maison Dimension Tracking Table'!V3 -> Total: 2
B7: Projects | C7: Owner | D7: Status
B8: {=_xlfn._xlws.FILTER('Maison Dimension Tracking Table'!E8:E40,'Maison Dimension Tracking Table'!V8:V40<>"")} -> Enrich project scaling | C8: {=_xlfn._xlws.FILTER('Maison Dimension Tracking Table'!D8:D40,'Maison Dimension Tracking Table'!V8:V40<>"")} -> Mars YU | D8: {=_xlfn._xlws.FILTER('Maison Dimension Tracking Table'!V8:V40,'Maison Dimension Tracking Table'!V8:V40<>"")} -> Run
B9: 【Advanced Journey 】High potential one-timer/repeater causal inference | C9: Chenlong WANG | D9: Q3-Pilot
B10: 【Client Community】CRM upskilling and community | C10: Candy HOU | D10: Done
B11: 【Clienteling】WeCom tools benchmark and feature innovation | C11: Qiwen MO | D11: Done
B12: VoC (NPS) | C12: Rikka CHEN | D12: Run
B13: Al training for omni-retail | C13: Rikka CHEN | D13: Ideation

Sheet Hublot
A1: Back <-
B2: ='Maison Dimension Tracking Table'!W2 -> Hublot
B4: ='Maison Dimension Tracking Table'!W7 -> Wendy CHEN | C4: ='Maison Dimension Tracking Table'!W3 -> Total: 1
B7: Projects | C7: Owner | D7: Status
B8: {=_xlfn._xlws.FILTER('Maison Dimension Tracking Table'!E8:E40,'Maison Dimension Tracking Table'!W8:W40<>"")} -> Enrich project scaling | C8: {=_xlfn._xlws.FILTER('Maison Dimension Tracking Table'!D8:D40,'Maison Dimension Tracking Table'!W8:W40<>"")} -> Mars YU | D8: {=_xlfn._xlws.FILTER('Maison Dimension Tracking Table'!W8:W40,'Maison Dimension Tracking Table'!W8:W40<>"")} -> Q1-Scale
B9: 【Clienteling】WeCom tools benchmark and feature innovation | C9: Qiwen MO | D9: Done

Sheet TAG Heuer
A1: Back <-
B2: ='Maison Dimension Tracking Table'!X2 -> TAG Heuer
B4: ='Maison Dimension Tracking Table'!Y7 -> Qiwen MO | C4: ='Maison Dimension Tracking Table'!Y3 -> Total: 4
B5: Kiki MI （Head of Communication)
B7: Projects | C7: Owner | D7: Status
B8: {=_xlfn._xlws.FILTER('Maison Dimension Tracking Table'!E8:E40,'Maison Dimension Tracking Table'!X8:X40<>"")} -> 【Clienteling】WeCom tools benchmark and feature innovation | C8: {=_xlfn._xlws.FILTER('Maison Dimension Tracking Table'!D8:D40,'Maison Dimension Tracking Table'!X8:X40<>"")} -> Qiwen MO | D8: {=_xlfn._xlws.FILTER('Maison Dimension Tracking Table'!X8:X40,'Maison Dimension Tracking Table'!X8:X40<>"")} -> Done
B9: 【KOS】AI solutions (scanning, content assistant, task management ) | C9: TBD | D9: Ideation
B10: 【Gen AI Content Hub】Asset Production & Distribution - LucIA | C10: Qia CHEN | D10: Ideation
B11: GEO | C11: Yuanne CHANG | D11: Ideation
B12: KOS Post Agent - to be evaluated | D12: Ideation

Sheet Zenith
A1: Back <-
B2: ='Maison Dimension Tracking Table'!Y2 -> Zenith
B4: ='Maison Dimension Tracking Table'!Y7 -> Qiwen MO | C4: ='Maison Dimension Tracking Table'!Y3 -> Total: 4
B5: Kelly WU
B7: Projects | C7: Owner | D7: Status
B8: {=_xlfn._xlws.FILTER('Maison Dimension Tracking Table'!E8:E40,'Maison Dimension Tracking Table'!Y8:Y40<>"")} -> Enrich project scaling | C8: {=_xlfn._xlws.FILTER('Maison Dimension Tracking Table'!D8:D40,'Maison Dimension Tracking Table'!Y8:Y40<>"")} -> Mars YU | D8: {=_xlfn._xlws.FILTER('Maison Dimension Tracking Table'!Y8:Y40,'Maison Dimension Tracking Table'!Y8:Y40<>"")} -> Q4-Scale
B9: Al training for omni-retail | C9: Rikka CHEN | D9: Ideation
B10: 【Gen AI Content Hub】Asset Production & Distribution | C10: Qia CHEN | D10: Q2-Pilot
B11: GEO | C11: Yuanne CHANG | D11: Ideation

Sheet Perfume Dior
A1: Back <-
B2: ='Maison Dimension Tracking Table'!Z2 -> Perfume Christine Dior
B4: ='Maison Dimension Tracking Table'!Z7 -> Chenlong WANG | C4: ='Maison Dimension Tracking Table'!Z3 -> Total: 6
B5: AI Champion： Shen XU
B7: Projects | C7: Owner | D7: Status
B8: {=_xlfn._xlws.FILTER('Maison Dimension Tracking Table'!E8:E40,'Maison Dimension Tracking Table'!Z8:Z40<>"")} -> Enrich project scaling | C8: {=_xlfn._xlws.FILTER('Maison Dimension Tracking Table'!D8:D40,'Maison Dimension Tracking Table'!Z8:Z40<>"")} -> Mars YU | D8: {=_xlfn._xlws.FILTER('Maison Dimension Tracking Table'!Z8:Z40,'Maison Dimension Tracking Table'!Z8:Z40<>"")} -> Ideation
B9: 【Clienteling】Gen AI Client Knowledge | C9: Chenlong WANG | D9: Q3-Pilot
B10: 【Marketing Automation 】Personalized journeys through QA migration, upgrades, and orchestration | C10: Qiwen MO | D10: Q1-Scale
B11: 【Client Community】CRM upskilling and community | C11: Candy HOU | D11: Done
B12: 【Clienteling】WeCom tools benchmark and feature innovation | C12: Qiwen MO | D12: Done
B13: China AI omni landscape strategy playbook 2) Agentic commerce | C13: Wendy CHEN | D13: Ideation
B14: VoC (NPS) | C14: Rikka CHEN | D14: Run
B15: Marketing Mix Modeling | C15: Qia CHEN | D15: Q4-Pilot
B16: GEO | C16: Yuanne CHANG | D16: Ideation | I16: Digital project budget change vs. B25 | J16: 略涨
I17: EC project budget change vs. B25 | J17: 持平
I18: AI project budget change vs. B25 | J18: 持平
I19: AI project planning | J19: 无
I20: EC growth rate target | J20: 无
B84: AI roadmap with PCD global | E84: 46128
B86: Matthieu NICOU， Melanie BOUVIER， Luciana DEGOES， Karine DAEGOS
B89: 1. Automated MMM is hard, we can consider traditional MMM instead
B90: 2. MaIA is not good enough, we will upgrade it in China soon
B91: 3. RAI committee should have right to kill project
B92: 4. Two RAIS, global and china, need to share with each other
B93: 5. Define the clear collobration between platform and us, roles and responsibilities
B94: 6 Agentic commerence is not only about GEO, which will open to public eventually. We should control the tone of voice and RAG

Sheet Guerlain
A1: Back <-
B2: ='Maison Dimension Tracking Table'!AA2 -> Guerlain
B4: ='Maison Dimension Tracking Table'!AA7 -> Rikka CHEN | C4: ='Maison Dimension Tracking Table'!AA3 -> Total: 9
B7: Projects | C7: Owner | D7: Status | E7: Remarks
B8: {=_xlfn._xlws.FILTER('Maison Dimension Tracking Table'!E8:E40,'Maison Dimension Tracking Table'!AA8:AA40<>"")} -> Enrich project scaling | C8: {=_xlfn._xlws.FILTER('Maison Dimension Tracking Table'!D8:D40,'Maison Dimension Tracking Table'!AA8:AA40<>"")} -> Mars YU | D8: {=_xlfn._xlws.FILTER('Maison Dimension Tracking Table'!AA8:AA40,'Maison Dimension Tracking Table'!AA8:AA40<>"")} -> Ideation | E8: Strong interest by HQ
B9: 【Marketing Automation 】Personalized journeys through QA migration, upgrades, and orchestration | C9: Qiwen MO | D9: Q1-Scale
B10: 【Clienteling】Gen AI Contextual Outreach | C10: Candy HOU | D10: Q3-Pilot
B11: 【Client Community】CRM upskilling and community | C11: Candy HOU | D11: Done
B12: 【Clienteling】WeCom tools benchmark and feature innovation | C12: Qiwen MO | D12: Done | E12: Top priority；希望不是campaign-based，而是长期sustainable的
B13: 【KOS】AI solutions (scanning, content assistant, task management ) | C13: TBD | D13: Q3-Pilot | E13: EC已经做了微信MNP/官网的购后弹窗，正在讨论Retail NPS的roadmap/budget，总部已经align供应商为众言
B14: China AI omni landscape strategy playbook 2) Agentic commerce | C14: Wendy CHEN | D14: Q3-Pilot | E14: Vendor selection process for PoC
B15: VoC (NPS) | C15: Rikka CHEN | D15: Run | E15: Top priority，主要针对抖音千川，现在是抖P月费里可能包了200张图（100原创、100二创或KOL授权），更多的图片就需要按rate card来，每个月花的钱很多，希望看怎么能够生成一些结合DY热点趋势的图+更加cost-efficiency。但目前这部分素材没有被mkt approve（一直以来的工作流）也瞒着总部。Mkt assets主要是明星和local campaign（520/七夕/618/38/双十一）by campaign找agency做素材，agency会使用AI做moodboard，但实际创作不能使用AI
B16: Al training for omni-retail | C16: Rikka CHEN | D16: Q4-Pilot | E16: Eric很愿意参与pilot
B17: 【Gen AI Content Hub】Asset Production & Distribution | C17: Qia CHEN | D17: Ideation
B18: Marketing Mix Modeling | C18: Qia CHEN | D18: Ideation
B19: GEO | C19: Yuanne CHANG | D19: Q3-Pilot

Sheet Beauty Div
A1: Back <-
B2: ='Maison Dimension Tracking Table'!AB2 -> Beauty Division
B4: ='Maison Dimension Tracking Table'!AB7 -> Wendy CHEN | C4: ='Maison Dimension Tracking Table'!AB3 -> Total: 4
B7: Projects | C7: Owner | D7: Status
B8: {=_xlfn._xlws.FILTER('Maison Dimension Tracking Table'!E8:E40,'Maison Dimension Tracking Table'!AB8:AB40<>"")} -> 【Advanced Journey 】Product Recom DREAM 2.0 | C8: {=_xlfn._xlws.FILTER('Maison Dimension Tracking Table'!D8:D40,'Maison Dimension Tracking Table'!AB8:AB40<>"")} -> Chenlong WANG | D8: {=_xlfn._xlws.FILTER('Maison Dimension Tracking Table'!AB8:AB40,'Maison Dimension Tracking Table'!AB8:AB40<>"")} -> Ideation
B9: 【Clienteling】Gen AI Contextual Outreach | C9: Candy HOU | D9: Q3-Pilot
B10: 【Client Community】CRM upskilling and community | C10: Candy HOU | D10: Done
B11: 【KOS】AI solutions (scanning, content assistant, task management ) | C11: TBD | D11: Q3-Pilot
B12: VoC (NPS) | C12: Rikka CHEN | D12: Run
B13: 【Gen AI Content Hub】Asset Production & Distribution - LucIA | C13: Qia CHEN | D13: Q2-Pilot

Sheet Sephora
A1: Back <-
B2: ='Maison Dimension Tracking Table'!AC2 -> Sephora
B4: ='Maison Dimension Tracking Table'!AC7 -> Qia CHEN | C4: ='Maison Dimension Tracking Table'!AC3 -> Total: 6
A5: AI Champion | B5: Lavender SHENG
B7: Projects with LVMH Digital | C7: Owner | D7: Status | F7: Projects led by Sephora in-house | G7: Status
B8: {=_xlfn._xlws.FILTER('Maison Dimension Tracking Table'!E8:E40,'Maison Dimension Tracking Table'!AC8:AC40<>"")} -> Enrich project scaling | C8: {=_xlfn._xlws.FILTER('Maison Dimension Tracking Table'!D8:D40,'Maison Dimension Tracking Table'!AC8:AC40<>"")} -> Mars YU | D8: {=_xlfn._xlws.FILTER('Maison Dimension Tracking Table'!AC8:AC40,'Maison Dimension Tracking Table'!AC8:AC40<>"")} -> Q4-Pilot | F8: Smart Search- Tencent Magic Agent (next best product, offer, content) | G8: Pilot in 2026 for product, rest for 2027
B9: China AI omni landscape strategy playbook 2) Agentic commerce | C9: Wendy CHEN | D9: Q4-Pilot | F9: Smart Replenishment | G9: Pilot in 2026
B10: VoC (NPS) | C10: Rikka CHEN | D10: Run | F10: Product Recommendation (similar product, complementary product, out-of-stock) | G10: Pilot in 2026
B11: Al training for omni-retail | C11: Rikka CHEN | D11: Q4-Pilot | F11: Personalise Ordering | G11: Ideation in 2027
B12: 【Gen AI Content Hub】Asset Production & Distribution | C12: Qia CHEN | D12: Q3-Pilot | F12: CRM Detection (churn detection, 2nd purchase for one time user) | G12: Pilot in 2026
B13: 【Gen AI Content Hub】Asset Production & Distribution - LucIA | C13: Qia CHEN | D13: Q2-Scale | F13: Gen AI for Product Review | G13: Pilot in 2026
B14: GEO | C14: Yuanne CHANG | D14: Q4-Pilot | F14: Chatbot on Dragon (self-owned channel) | G14: Pilot in 2026
F15: GEA- visibility on Search Engine | G15: Ideation in 2027
F16: Smart Demand Planning (predict novelty, store assortment, AI-assisted Merch) | G16: Ideation in 2027
F17: Space Planning | G17: Ideation in 2026
F18: AI Staff Recruiting | G18: Ideation in 2026
F19: Employee HR Assistant | G19: Scaled in 2026
F20: Talk to my number | G20: Ideation in 2027
B21: Key Challenges | F21: Personalised communication (content generation, customer interaction) | G21: Pilot in 2026
B22: 白卡members conversion & upgrade
B23: recruiting new members registration, esp. online
B25: Key Features & Data of Sephora
B26: Heavily within Tencent ecosytem, with their strong online % of self-owned channel (Dragon)
B27: High Local Saying over strategy, image assets-one of the three independent delivery centres
B28: 5M member data, 300+ offline stores

Sheet MHD
A1: Back <-
B2: ='Maison Dimension Tracking Table'!AD2 -> MHD
B4: ='Maison Dimension Tracking Table'!AD7 -> Mars Yu | C4: ='Maison Dimension Tracking Table'!AD3 -> Total: 1
B7: Projects | C7: Owner | D7: Status
B8: {=_xlfn._xlws.FILTER('Maison Dimension Tracking Table'!E8:E40,'Maison Dimension Tracking Table'!AD8:AD40<>"")} -> Enrich project scaling | C8: {=_xlfn._xlws.FILTER('Maison Dimension Tracking Table'!D8:D40,'Maison Dimension Tracking Table'!AD8:AD40<>"")} -> Mars YU | D8: {=_xlfn._xlws.FILTER('Maison Dimension Tracking Table'!AD8:AD40,'Maison Dimension Tracking Table'!AD8:AD40<>"")} -> Q3-Scale
B9: 【Client Community】CRM upskilling and community | C9: Candy HOU | D9: Done

Sheet Original tracking table
C4: Theme | D4: Team | E4: Projects | F4: Maisons | G4: Accountable
C5: Client development | D5: Josh | E5: QA Journeys migration and upgrades, design & orchestration | F5: Bvlgari, CDC, Loro Piana (2025 Q4), Tiffany, Chaumet (Q1), Fendi (Q2), Loewe(Q3), Celine, Givenchy, Sephora, PCD, LV (Q4) | G5: Qiwen
E6: GenAI content tagging rollout | F6: Tiffany, Bvlgari (Q2), LV (Q3) | G6: Qiwen
E7: GenAI in Clienteling: contextual outreach and upgrades | F7: Tiffany (2025 Q4), Bvlgari (Q2) | G7: Candy
E8: GenAI in Clienteling: client summary | F8: PCD (Q2), Loro Piana (Q4) | G8: Qiwen
E9: GenAI in Retail training role play | F9: Fendi (Q1), Beauty Division (Q3), [Fashion Masions] | G9: Patrick
E10: CRM upskilling and community (Clienteling Certificate with House) | F10: All LVMH Maisons | G10: Candy
E11: Clienteling tools: WeCom benchmark and feature innovation | F11: All LVMH Maisons (Q4) | G11: Patrick
E12: KOS solutions (include AI scanning, content assistant, task management ) | F12: Loewe, Celine, Tiffany, Bvlgari | G12: Chen
E13: KOS operations & governance: scaling, performance governance incl. media | F13: All LVMH Maisons – incl. PCD, CDC | G13: Chen
E14: KOS community building & KOS Day | F14: All LVMH Maisons (Sep/Oct.) | G14: Chen
E15: KOS upscaling incl. training, daily operational coach | F15: Bvlgari, Tiffany, Givenchy, Fendi, Rimowa, Kenzo | G15: Chen
C16: Omni-retail | D16: Rachael | E16: NPS scaling and GenAI enhancement | F16: CDC(Q1), Loewe, Celine (Q2), Fendi (Q4) | G16: Rikka
E17: GenAI/AI in Ecommerce (total-look swap) | F17: Givenchy, Fendi, Berluti (Q1), Loewe | G17: Qinyin
E18: GenAI/AI in Ecommerce (product recommendation, smart search) | F18: Celine (Q2) | G18: Wendy
E19: EC A/B testing | F19: Bvlgari | G19: Wendy
E20: Tracking Lab | F20: Loro Piara, Chaumet, Tiffany (Q1) | G20: Wendy
E21: E-Commerce strategic growth and governance | F21: Givenchy (reinitial) | G21: Wendy
E22: Unauthorized reduction (with brand protection team) | F22: All LVMH Maisons | G22: Wendy
E23: Online intelligence reporting | F23: All LVMH Maisons | G23: Wendy
E24: GenAI/AI in CSC | F24: CDC, [Rimowa] | G24: Qinyin
E25: Partnership – forging new including AI/genAI partners, elevating existing | F25: All LVMH Maisons | G25: Yuanne
C26: Data & AI | D26: Mars | E26: Enlight global dashboard launch and KOS dashboard | F26: All LVMH Maisons (KOS Dashboard Q2) | G26: Mars
E27: Enrich scaling | F27: LV/CDC, Berluti, Hublot, Givenchy | G27: Po
E28: AI/GenAI factory scaling with new algorithms (styling) | F28: All FLG and W&J Maisons, styling for Celine (Q2) | G28: Chenlong/Livia/Xintong
E29: Data Governance (Enrich audit , data minimization) | F29: All LVMH Maisons (Enrich audit Q2) | G29: Mars/Qiwen
E30: Responsible AI | F30: All LVMH Maisons (AI card Q1) | G30: Mars/Anny/ Romain
E31: GenAI/AI content creation group deal (SKAI, Lucia, Omi, Grip, Resizing) | F31: All LVMH Maisons | G31: Mars
C38: Q1
C39: Q2
C40: Q3
C41: Q4
C42: Prospect
C43: N/A

Sheet Maison dimension table
D1: DATA & AI | Q1: CLIENT DEVELOPMENT | AA1: OMNI_RETAIL
A2: Division | B2: Maison(22) | C2: Key Account | D2: Enrich project scaling | E2: High potential one-timer/repeater | F2: High potential one-timer/repeater causal inference | G2: High potential client list orchestration | H2: High potential propensity for collection | I2: High potential VIC detection | J2: DREAM 2.0 | K2: Content intelligence | L2: Total-look recommendation | M2: Smart Search for EC | N2: Client Knowledge | O2: Contextual Outreach | P2: Contextual Outreach 2.0 | Q2: QA Journeys migration and upgrades, design & orchestration | R2: GenAI content tagging rollout | S2: GenAI in Clienteling: contextual outreach and upgrades | T2: GenAI in Clienteling: client summary | U2: CRM upskilling and community (Clienteling Certificate with House) | V2: Clienteling tools: WeCom benchmark and feature innovation | W2: KOS solutions (include AI scanning, content assistant, task management ) | X2: KOS operations & governance: scaling, performance governance incl. media | Y2: KOS community building & KOS Day | Z2: KOS upscaling incl. training, daily operational coach | AA2: NPS scaling and GenAI enhancement | AB2: GenAI/AI in Ecommerce/Social/Clienteling (total-look swap) | AC2: GenAI/AI in Ecommerce (product recommendation, smart search) | AD2: EC A/B testing | AE2: Tracking Lab | AF2: E-Commerce strategic growth and governance | AG2: Unauthorized reduction (with brand protection team) | AH2: Online intelligence reporting | AI2: GenAI/AI in CSC | AJ2: GenAI in Retail training role play | AK2: Geo | AL2: Agentic Commerce
D3: Mars YU / Xintong YAN | E3: Chenlong WANG | F3: Chenlong WANG | G3: Xintong YAN | H3: Chenlong WANG | I3: Chenlong WANG | J3: Chenlong WANG | K3: Livia GAO | L3: Livia GAO | M3: Chenlong WANG | N3: Chenlong WANG | O3: Chenlong WANG | P3: Chenlong WANG | Q3: Qiwen MO | R3: Qiwen MO | S3: Candy HOU | T3: Qiwen MO | U3: Candy HOU | V3: Qiwen MO | W3: Chen JIA | X3: Chen JIA | Y3: Chen JIA | Z3: Chen JIA | AA3: Rikka CHEN | AB3: Qia CHEN | AC3: Wendy CHEN | AD3: Wendy CHEN | AE3: Wendy CHEN | AF3: Wendy CHEN | AG3: Wendy CHEN | AH3: Wendy CHEN | AI3: Qia CHEN | AJ3: Rikka CHEN | AK3: Rachael JIANG | AL3: Yuanne CHANG
D4: =_xlfn.TEXTJOIN(" | ",TRUE,"Q1: "&COUNTIF(D5:D26,"Q1"),"Q2: "&COUNTIF(D5:D26,"Q2"),"Q3: "&COUNTIF(D5:D26,"Q3"),"Q4: "&COUNTIF(D5:D26,"Q4"),"Pros: "&COUNTIF(D5:D26,"Prospect")) -> Q1: 2 | Q2: 1 | Q3: 0 | Q4: 0 | Pros: 2 | E4: =_xlfn.TEXTJOIN(" | ",TRUE,"Q1: "&COUNTIF(E5:E26,"Q1"),"Q2: "&COUNTIF(E5:E26,"Q2"),"Q3: "&COUNTIF(E5:E26,"Q3"),"Q4: "&COUNTIF(E5:E26,"Q4"),"Pros: "&COUNTIF(E5:E26,"Prospect")) -> Q1: 1 | Q2: 0 | Q3: 3 | Q4: 0 | Pros: 0 | F4: =_xlfn.TEXTJOIN(" | ",TRUE,"Q1: "&COUNTIF(F5:F26,"Q1"),"Q2: "&COUNTIF(F5:F26,"Q2"),"Q3: "&COUNTIF(F5:F26,"Q3"),"Q4: "&COUNTIF(F5:F26,"Q4"),"Pros: "&COUNTIF(F5:F26,"Prospect")) -> Q1: 0 | Q2: 0 | Q3: 0 | Q4: 1 | Pros: 0 | G4: =_xlfn.TEXTJOIN(" | ",TRUE,"Q1: "&COUNTIF(G5:G26,"Q1"),"Q2: "&COUNTIF(G5:G26,"Q2"),"Q3: "&COUNTIF(G5:G26,"Q3"),"Q4: "&COUNTIF(G5:G26,"Q4"),"Pros: "&COUNTIF(G5:G26,"Prospect")) -> Q1: 0 | Q2: 0 | Q3: 0 | Q4: 1 | Pros: 0 | H4: =_xlfn.TEXTJOIN(" | ",TRUE,"Q1: "&COUNTIF(H5:H26,"Q1"),"Q2: "&COUNTIF(H5:H26,"Q2"),"Q3: "&COUNTIF(H5:H26,"Q3"),"Q4: "&COUNTIF(H5:H26,"Q4"),"Pros: "&COUNTIF(H5:H26,"Prospect")) -> Q1: 1 | Q2: 0 | Q3: 1 | Q4: 0 | Pros: 0 | I4: =_xlfn.TEXTJOIN(" | ",TRUE,"Q1: "&COUNTIF(I5:I26,"Q1"),"Q2: "&COUNTIF(I5:I26,"Q2"),"Q3: "&COUNTIF(I5:I26,"Q3"),"Q4: "&COUNTIF(I5:I26,"Q4"),"Pros: "&COUNTIF(I5:I26,"Prospect")) -> Q1: 0 | Q2: 1 | Q3: 1 | Q4: 0 | Pros: 0 | J4: =_xlfn.TEXTJOIN(" | ",TRUE,"Q1: "&COUNTIF(J5:J26,"Q1"),"Q2: "&COUNTIF(J5:J26,"Q2"),"Q3: "&COUNTIF(J5:J26,"Q3"),"Q4: "&COUNTIF(J5:J26,"Q4"),"Pros: "&COUNTIF(J5:J26,"Prospect")) -> Q1: 0 | Q2: 3 | Q3: 3 | Q4: 0 | Pros: 0 | K4: =_xlfn.TEXTJOIN(" | ",TRUE,"Q1: "&COUNTIF(K5:K26,"Q1"),"Q2: "&COUNTIF(K5:K26,"Q2"),"Q3: "&COUNTIF(K5:K26,"Q3"),"Q4: "&COUNTIF(K5:K26,"Q4"),"Pros: "&COUNTIF(K5:K26,"Prospect")) -> Q1: 1 | Q2: 1 | Q3: 0 | Q4: 0 | Pros: 0 | ... AL4: =_xlfn.TEXTJOIN(" | ",TRUE,"Q1: "&COUNTIF(AL5:AL26,"Q1"),"Q2: "&COUNTIF(AL5:AL26,"Q2"),"Q3: "&COUNTIF(AL5:AL26,"Q3"),"Q4: "&COUNTIF(AL5:AL26,"Q4"),"Pros: "&COUNTIF(AL5:AL26,"Prospect")) -> Q1: 0 | Q2: 0 | Q3: 0 | Q4: 0 | Pros: 3
A5: FLG | B5: Louis Vitton | C5: Rachael JIANG | D5: Prospect | Q5: Q4 | R5: Q3 | U5: Prospect | V5: Q4 | AA5: Q1 | AB5: Prospect | AC5: Q1 | AF5: Prospect | AK5: Prospect
B6: Christine Dior Couture | C6: Mars YU | D6: Prospect | AA6: Q1 | AG6: Q1 | AH6: Q1 | AI6: Q1
B7: Loro Piana | C7: Rachael JIANG | E7: Q3 | J7: Q3 | N7: Q4 | T7: Q4 | AA7: Q1 | AB7: Prospect | AD7: Prospect | AE7: Q1 | AG7: Q1 | AH7: Q1
B8: Fendi | C8: Wendy CHEN | E8: Q3 | Q8: Q2 | AA8: Prospect | AB8: Q1 | AG8: Q1 | AH8: Q1 | AJ8: Q1
B9: Celine | C9: Livia GAO | J9: Q2 | L9: Q3 | M9: Q4 | Q9: Q4 | AA9: Q2 | AC9: Q2 | AE9: Prospect | AG9: Q1 | AH9: Q1
B10: Loewe | C10: Chen JIA | D10: Q1 | E10: Q1 | I10: Q2 | J10: Q3 | Q10: Q3 | AA10: Q2 | AB10: Prospect | AG10: Q1 | AH10: Prospect | AJ10: Prospect
B11: Givenchy | C11: Xintong YAN | Q11: Q4 | AB11: Q1 | AF11: Prospect | AG11: Q1 | AH11: Q1
B12: Kenzo | C12: Chen JIA
B13: Berluti | C13: Yuanne CHANG | D13: Q2 | AB13: Prospect | AF13: N/A | AH13: Q1 | AJ13: Prospect
B14: Marc Jocobs | C14: Chen JIA | AH14: Q1
B15: Rimowa | C15: Wendy CHEN | AA15: Q1 | AD15: Prospect | AE15: Q2 | AF15: N/A | AH15: Q1 | AI15: Prospect
A16: W&J | B16: Tiffany | C16: Candy HOU | G16: Q4 | H16: Q3 | I16: Q3 | J16: Q3 | K16: Q1 | P16: Q3 | Q16: Q1 | R16: Q2 | S16: Q1 | AA16: Q2 | AB16: Prospect | AE16: Q1 | AF16: N/A | AG16: Q1 | AH16: Q1 | AI16: Prospect | AK16: Prospect
B17: Bvlgari | C17: Chenlong WANG | F17: Q4 | H17: Q1 | J17: Q2 | K17: Q2 | O17: Q2 | P17: Q3 | R17: Q2 | S17: Q2 | AA17: Q1 | AD17: Q2 | AF17: N/A | AG17: Q1 | AH17: Q1
B18: Chaumet | C18: Qiwen MO | J18: Q2 | Q18: Q1 | AA18: Q1 | AE18: Q1 | AG18: Q1 | AH18: Q1
B19: Fred | C19: Rikka CHEN | E19: Q3 | AA19: Q1 | AF19: N/A | AG19: Q1
B20: Hublot | C20: Wendy CHEN | D20: Q1 | AE20: Prospect
B21: TAG Heuer | C21: Qiwen MO | AF21: N/A
B22: Zenith | C22: Qiwen MO | AF22: N/A
A23: Beauty | B23: Perfume Christine Dior | C23: Chenlong WANG | N23: Q2 | Q23: Q4 | T23: Q2 | U23: Prospect | AA23: Q1 | AF23: N/A | AL23: Prospect
B24: Guerlain | C24: Candy HOU | U24: Prospect | AA24: Q1 | AF24: N/A | AL24: Prospect
B25: Beauty Division (Givenchy,Kenzo, Loewe, Benefit, Makeup forever, ADP, Fresh) | C25: Wendy CHEN | S25: Prospect | AA25: Q1 | AF25: N/A | AJ25: Q3 | AL25: Prospect
A26: Selective Retailing | B26: Sephora | C26: Qia CHEN | Q26: Q4 | AA26: Q1 | AF26: N/A
